[
  {
    "title": "BB-Spiele \u2013 Regional Championship Store Qualifier - Modern",
    "start": "2026-04-04T11:00:00+02:00",
    "end": "2026-04-04T14:00:00+02:00",
    "location": "BB-Spiele",
    "url": "https://www.bb-spiele.de",
    "description": "Gewinner des WPN Qualifier erh\u00e4lt 1 Slot f\u00fcr den Regional Championship.",
    "all_day": false
  },
  {
    "title": "Funtainment \u2013 Friday Night Magic: Modern",
    "start": "2026-03-27T17:00:00+01:00",
    "end": "2026-03-27T20:00:00+01:00",
    "location": "FUNtainment M\u00fcnchen",
    "url": "https://www.funtainment.de",
    "description": "Buche Deinen Platz f\u00fcr dieses Event",
    "all_day": false
  },
  {
    "title": "Funtainment \u2013 Friday Night Magic: Modern",
    "start": "2026-04-10T17:00:00+02:00",
    "end": "2026-04-10T20:00:00+02:00",
    "location": "FUNtainment M\u00fcnchen",
    "url": "https://www.funtainment.de",
    "description": "Buche Deinen Platz f\u00fcr dieses Event",
    "all_day": false
  },
  {
    "title": "Funtainment \u2013 Friday Night Magic: Modern",
    "start": "2026-04-17T17:00:00+02:00",
    "end": "2026-04-17T20:00:00+02:00",
    "location": "FUNtainment M\u00fcnchen",
    "url": "https://www.funtainment.de",
    "description": "Buche Deinen Platz f\u00fcr dieses Event",
    "all_day": false
  },
  {
    "title": "Funtainment \u2013 Friday Night Magic: Modern",
    "start": "2026-04-24T17:00:00+02:00",
    "end": "2026-04-24T20:00:00+02:00",
    "location": "FUNtainment M\u00fcnchen",
    "url": "https://www.funtainment.de",
    "description": "Buche Deinen Platz f\u00fcr dieses Event",
    "all_day": false
  },
  {
    "title": "Deck & Dice \u2013 After Work Standard - 19:00 Uhr",
    "start": "2026-03-23T19:00:00+01:00",
    "end": "2026-03-23T22:00:00+01:00",
    "location": "Deck & Dice Munich",
    "url": "https://www.dd-munich.de",
    "description": "",
    "all_day": false
  },
  {
    "title": "Deck & Dice \u2013 After Work Modern - 19:00 Uhr",
    "start": "2026-03-24T19:00:00+01:00",
    "end": "2026-03-24T22:00:00+01:00",
    "location": "Deck & Dice Munich",
    "url": "https://www.dd-munich.de",
    "description": "",
    "all_day": false
  },
  {
    "title": "Deck & Dice \u2013 After Work Legacy",
    "start": "2026-03-25T19:00:00+01:00",
    "end": "2026-03-25T22:00:00+01:00",
    "location": "Deck & Dice Munich",
    "url": "https://www.dd-munich.de",
    "description": "",
    "all_day": false
  },
  {
    "title": "Deck & Dice \u2013 After Work Premodern 19:00 Uhr",
    "start": "2026-03-26T19:00:00+01:00",
    "end": "2026-03-26T22:00:00+01:00",
    "location": "Deck & Dice Munich",
    "url": "https://www.dd-munich.de",
    "description": "",
    "all_day": false
  },
  {
    "title": "Deck & Dice \u2013 Friday Night Standard 18.30",
    "start": "2026-03-27T18:30:00+01:00",
    "end": "2026-03-27T21:30:00+01:00",
    "location": "Deck & Dice Munich",
    "url": "https://www.dd-munich.de",
    "description": "",
    "all_day": false
  },
  {
    "title": "Fanfinity \u2013 Magic Spotlight Series London 2026",
    "start": "2026-05-08T00:00:00",
    "end": "2026-05-11T00:00:00",
    "location": "Online",
    "url": "https://www.fanfinity.gg/event/magic-spotlight-series-london-2026/",
    "description": "Event von Fanfinity: Magic Spotlight Series London 2026\nhttps://www.fanfinity.gg/event/magic-spotlight-series-london-2026/",
    "all_day": true
  },
  {
    "title": "Fanfinity \u2013 Ultimate Guard European Magic Series \u2013 Regional Championship \u2013 Prague 2026",
    "start": "2026-05-29T00:00:00",
    "end": "2026-06-01T00:00:00",
    "location": "Online",
    "url": "https://www.fanfinity.gg/event/ultimate-guard-european-magic-series-regional-championship-prague-2026/",
    "description": "Event von Fanfinity: Ultimate Guard European Magic Series \u2013 Regional Championship \u2013 Prague 2026\nhttps://www.fanfinity.gg/event/ultimate-guard-european-magic-series-regional-championship-prague-2026/",
    "all_day": true
  },
  {
    "title": "Fanfinity \u2013 Magic Spotlight Series Brussels 2026",
    "start": "2026-07-24T00:00:00",
    "end": "2026-07-27T00:00:00",
    "location": "Online",
    "url": "https://www.fanfinity.gg/event/magic-spotlight-series-brussels-2026/",
    "description": "Event von Fanfinity: Magic Spotlight Series Brussels 2026\nhttps://www.fanfinity.gg/event/magic-spotlight-series-brussels-2026/",
    "all_day": true
  },
  {
    "title": "Fanfinity \u2013 Ultimate Guard European Magic Series Regional Championship Ghent 2026",
    "start": "2026-10-09T00:00:00",
    "end": "2026-10-12T00:00:00",
    "location": "Online",
    "url": "https://www.fanfinity.gg/event/ultimate-guard-european-magic-series-regional-championship-ghent-2026/",
    "description": "Event von Fanfinity: Ultimate Guard European Magic Series Regional Championship Ghent 2026\nhttps://www.fanfinity.gg/event/ultimate-guard-european-magic-series-regional-championship-ghent-2026/",
    "all_day": true
  },
  {
    "title": "Deck & Dice \u2013 After Work Standard - 19:00 Uhr",
    "start": "2026-03-30T19:00:00+02:00",
    "end": "2026-03-30T22:00:00+02:00",
    "location": "Deck & Dice Munich",
    "url": "https://www.dd-munich.de",
    "description": "",
    "all_day": false
  },
  {
    "title": "Deck & Dice \u2013 After Work Standard - 19:00 Uhr",
    "start": "2026-04-13T19:00:00+02:00",
    "end": "2026-04-13T22:00:00+02:00",
    "location": "Deck & Dice Munich",
    "url": "https://www.dd-munich.de",
    "description": "",
    "all_day": false
  },
  {
    "title": "Deck & Dice \u2013 After Work Standard - 19:00 Uhr",
    "start": "2026-04-20T19:00:00+02:00",
    "end": "2026-04-20T22:00:00+02:00",
    "location": "Deck & Dice Munich",
    "url": "https://www.dd-munich.de",
    "description": "",
    "all_day": false
  },
  {
    "title": "Deck & Dice \u2013 After Work Standard - 19:00 Uhr",
    "start": "2026-04-27T19:00:00+02:00",
    "end": "2026-04-27T22:00:00+02:00",
    "location": "Deck & Dice Munich",
    "url": "https://www.dd-munich.de",
    "description": "",
    "all_day": false
  },
  {
    "title": "Deck & Dice \u2013 After Work Standard - 19:00 Uhr",
    "start": "2026-05-04T19:00:00+02:00",
    "end": "2026-05-04T22:00:00+02:00",
    "location": "Deck & Dice Munich",
    "url": "https://www.dd-munich.de",
    "description": "",
    "all_day": false
  },
  {
    "title": "Deck & Dice \u2013 After Work Standard - 19:00 Uhr",
    "start": "2026-05-11T19:00:00+02:00",
    "end": "2026-05-11T22:00:00+02:00",
    "location": "Deck & Dice Munich",
    "url": "https://www.dd-munich.de",
    "description": "",
    "all_day": false
  },
  {
    "title": "Deck & Dice \u2013 After Work Standard - 19:00 Uhr",
    "start": "2026-05-18T19:00:00+02:00",
    "end": "2026-05-18T22:00:00+02:00",
    "location": "Deck & Dice Munich",
    "url": "https://www.dd-munich.de",
    "description": "",
    "all_day": false
  },
  {
    "title": "Deck & Dice \u2013 After Work Standard - 19:00 Uhr",
    "start": "2026-06-01T19:00:00+02:00",
    "end": "2026-06-01T22:00:00+02:00",
    "location": "Deck & Dice Munich",
    "url": "https://www.dd-munich.de",
    "description": "",
    "all_day": false
  },
  {
    "title": "Deck & Dice \u2013 After Work Standard - 19:00 Uhr",
    "start": "2026-06-08T19:00:00+02:00",
    "end": "2026-06-08T22:00:00+02:00",
    "location": "Deck & Dice Munich",
    "url": "https://www.dd-munich.de",
    "description": "",
    "all_day": false
  },
  {
    "title": "Deck & Dice \u2013 After Work Standard - 19:00 Uhr",
    "start": "2026-06-15T19:00:00+02:00",
    "end": "2026-06-15T22:00:00+02:00",
    "location": "Deck & Dice Munich",
    "url": "https://www.dd-munich.de",
    "description": "",
    "all_day": false
  },
  {
    "title": "Deck & Dice \u2013 After Work Standard - 19:00 Uhr",
    "start": "2026-06-22T19:00:00+02:00",
    "end": "2026-06-22T22:00:00+02:00",
    "location": "Deck & Dice Munich",
    "url": "https://www.dd-munich.de",
    "description": "",
    "all_day": false
  },
  {
    "title": "Deck & Dice \u2013 After Work Standard - 19:00 Uhr",
    "start": "2026-06-29T19:00:00+02:00",
    "end": "2026-06-29T22:00:00+02:00",
    "location": "Deck & Dice Munich",
    "url": "https://www.dd-munich.de",
    "description": "",
    "all_day": false
  },
  {
    "title": "Deck & Dice \u2013 After Work Standard - 19:00 Uhr",
    "start": "2026-07-06T19:00:00+02:00",
    "end": "2026-07-06T22:00:00+02:00",
    "location": "Deck & Dice Munich",
    "url": "https://www.dd-munich.de",
    "description": "",
    "all_day": false
  },
  {
    "title": "Deck & Dice \u2013 After Work Standard - 19:00 Uhr",
    "start": "2026-07-13T19:00:00+02:00",
    "end": "2026-07-13T22:00:00+02:00",
    "location": "Deck & Dice Munich",
    "url": "https://www.dd-munich.de",
    "description": "",
    "all_day": false
  },
  {
    "title": "Deck & Dice \u2013 After Work Standard - 19:00 Uhr",
    "start": "2026-07-20T19:00:00+02:00",
    "end": "2026-07-20T22:00:00+02:00",
    "location": "Deck & Dice Munich",
    "url": "https://www.dd-munich.de",
    "description": "",
    "all_day": false
  },
  {
    "title": "Deck & Dice \u2013 After Work Standard - 19:00 Uhr",
    "start": "2026-07-27T19:00:00+02:00",
    "end": "2026-07-27T22:00:00+02:00",
    "location": "Deck & Dice Munich",
    "url": "https://www.dd-munich.de",
    "description": "",
    "all_day": false
  },
  {
    "title": "Deck & Dice \u2013 After Work Standard - 19:00 Uhr",
    "start": "2026-08-03T19:00:00+02:00",
    "end": "2026-08-03T22:00:00+02:00",
    "location": "Deck & Dice Munich",
    "url": "https://www.dd-munich.de",
    "description": "",
    "all_day": false
  },
  {
    "title": "Deck & Dice \u2013 After Work Standard - 19:00 Uhr",
    "start": "2026-08-10T19:00:00+02:00",
    "end": "2026-08-10T22:00:00+02:00",
    "location": "Deck & Dice Munich",
    "url": "https://www.dd-munich.de",
    "description": "",
    "all_day": false
  },
  {
    "title": "Deck & Dice \u2013 After Work Standard - 19:00 Uhr",
    "start": "2026-08-17T19:00:00+02:00",
    "end": "2026-08-17T22:00:00+02:00",
    "location": "Deck & Dice Munich",
    "url": "https://www.dd-munich.de",
    "description": "",
    "all_day": false
  },
  {
    "title": "Deck & Dice \u2013 After Work Standard - 19:00 Uhr",
    "start": "2026-08-24T19:00:00+02:00",
    "end": "2026-08-24T22:00:00+02:00",
    "location": "Deck & Dice Munich",
    "url": "https://www.dd-munich.de",
    "description": "",
    "all_day": false
  },
  {
    "title": "Deck & Dice \u2013 After Work Standard - 19:00 Uhr",
    "start": "2026-08-31T19:00:00+02:00",
    "end": "2026-08-31T22:00:00+02:00",
    "location": "Deck & Dice Munich",
    "url": "https://www.dd-munich.de",
    "description": "",
    "all_day": false
  },
  {
    "title": "Deck & Dice \u2013 After Work Standard - 19:00 Uhr",
    "start": "2026-09-07T19:00:00+02:00",
    "end": "2026-09-07T22:00:00+02:00",
    "location": "Deck & Dice Munich",
    "url": "https://www.dd-munich.de",
    "description": "",
    "all_day": false
  },
  {
    "title": "Deck & Dice \u2013 After Work Standard - 19:00 Uhr",
    "start": "2026-09-14T19:00:00+02:00",
    "end": "2026-09-14T22:00:00+02:00",
    "location": "Deck & Dice Munich",
    "url": "https://www.dd-munich.de",
    "description": "",
    "all_day": false
  },
  {
    "title": "Deck & Dice \u2013 After Work Standard - 19:00 Uhr",
    "start": "2026-09-21T19:00:00+02:00",
    "end": "2026-09-21T22:00:00+02:00",
    "location": "Deck & Dice Munich",
    "url": "https://www.dd-munich.de",
    "description": "",
    "all_day": false
  },
  {
    "title": "Deck & Dice \u2013 After Work Standard - 19:00 Uhr",
    "start": "2026-09-28T19:00:00+02:00",
    "end": "2026-09-28T22:00:00+02:00",
    "location": "Deck & Dice Munich",
    "url": "https://www.dd-munich.de",
    "description": "",
    "all_day": false
  },
  {
    "title": "Deck & Dice \u2013 After Work Standard - 19:00 Uhr",
    "start": "2026-10-05T19:00:00+02:00",
    "end": "2026-10-05T22:00:00+02:00",
    "location": "Deck & Dice Munich",
    "url": "https://www.dd-munich.de",
    "description": "",
    "all_day": false
  },
  {
    "title": "Deck & Dice \u2013 After Work Standard - 19:00 Uhr",
    "start": "2026-10-12T19:00:00+02:00",
    "end": "2026-10-12T22:00:00+02:00",
    "location": "Deck & Dice Munich",
    "url": "https://www.dd-munich.de",
    "description": "",
    "all_day": false
  },
  {
    "title": "Deck & Dice \u2013 After Work Standard - 19:00 Uhr",
    "start": "2026-10-19T19:00:00+02:00",
    "end": "2026-10-19T22:00:00+02:00",
    "location": "Deck & Dice Munich",
    "url": "https://www.dd-munich.de",
    "description": "",
    "all_day": false
  },
  {
    "title": "Deck & Dice \u2013 After Work Standard - 19:00 Uhr",
    "start": "2026-10-26T19:00:00+01:00",
    "end": "2026-10-26T22:00:00+01:00",
    "location": "Deck & Dice Munich",
    "url": "https://www.dd-munich.de",
    "description": "",
    "all_day": false
  },
  {
    "title": "Deck & Dice \u2013 After Work Standard - 19:00 Uhr",
    "start": "2026-11-02T19:00:00+01:00",
    "end": "2026-11-02T22:00:00+01:00",
    "location": "Deck & Dice Munich",
    "url": "https://www.dd-munich.de",
    "description": "",
    "all_day": false
  },
  {
    "title": "Deck & Dice \u2013 After Work Standard - 19:00 Uhr",
    "start": "2026-11-09T19:00:00+01:00",
    "end": "2026-11-09T22:00:00+01:00",
    "location": "Deck & Dice Munich",
    "url": "https://www.dd-munich.de",
    "description": "",
    "all_day": false
  },
  {
    "title": "Deck & Dice \u2013 After Work Standard - 19:00 Uhr",
    "start": "2026-11-16T19:00:00+01:00",
    "end": "2026-11-16T22:00:00+01:00",
    "location": "Deck & Dice Munich",
    "url": "https://www.dd-munich.de",
    "description": "",
    "all_day": false
  },
  {
    "title": "Deck & Dice \u2013 After Work Standard - 19:00 Uhr",
    "start": "2026-11-23T19:00:00+01:00",
    "end": "2026-11-23T22:00:00+01:00",
    "location": "Deck & Dice Munich",
    "url": "https://www.dd-munich.de",
    "description": "",
    "all_day": false
  },
  {
    "title": "Deck & Dice \u2013 After Work Standard - 19:00 Uhr",
    "start": "2026-11-30T19:00:00+01:00",
    "end": "2026-11-30T22:00:00+01:00",
    "location": "Deck & Dice Munich",
    "url": "https://www.dd-munich.de",
    "description": "",
    "all_day": false
  },
  {
    "title": "Deck & Dice \u2013 After Work Standard - 19:00 Uhr",
    "start": "2026-12-07T19:00:00+01:00",
    "end": "2026-12-07T22:00:00+01:00",
    "location": "Deck & Dice Munich",
    "url": "https://www.dd-munich.de",
    "description": "",
    "all_day": false
  },
  {
    "title": "Deck & Dice \u2013 After Work Standard - 19:00 Uhr",
    "start": "2026-12-14T19:00:00+01:00",
    "end": "2026-12-14T22:00:00+01:00",
    "location": "Deck & Dice Munich",
    "url": "https://www.dd-munich.de",
    "description": "",
    "all_day": false
  },
  {
    "title": "Deck & Dice \u2013 After Work Standard - 19:00 Uhr",
    "start": "2026-12-21T19:00:00+01:00",
    "end": "2026-12-21T22:00:00+01:00",
    "location": "Deck & Dice Munich",
    "url": "https://www.dd-munich.de",
    "description": "",
    "all_day": false
  },
  {
    "title": "Deck & Dice \u2013 After Work Standard - 19:00 Uhr",
    "start": "2026-12-28T19:00:00+01:00",
    "end": "2026-12-28T22:00:00+01:00",
    "location": "Deck & Dice Munich",
    "url": "https://www.dd-munich.de",
    "description": "",
    "all_day": false
  },
  {
    "title": "Deck & Dice \u2013 After Work Modern - 19:00 Uhr",
    "start": "2026-03-31T19:00:00+02:00",
    "end": "2026-03-31T22:00:00+02:00",
    "location": "Deck & Dice Munich",
    "url": "https://www.dd-munich.de",
    "description": "",
    "all_day": false
  },
  {
    "title": "Deck & Dice \u2013 After Work Modern - 19:00 Uhr",
    "start": "2026-04-07T19:00:00+02:00",
    "end": "2026-04-07T22:00:00+02:00",
    "location": "Deck & Dice Munich",
    "url": "https://www.dd-munich.de",
    "description": "",
    "all_day": false
  },
  {
    "title": "Deck & Dice \u2013 After Work Modern - 19:00 Uhr",
    "start": "2026-04-14T19:00:00+02:00",
    "end": "2026-04-14T22:00:00+02:00",
    "location": "Deck & Dice Munich",
    "url": "https://www.dd-munich.de",
    "description": "",
    "all_day": false
  },
  {
    "title": "Deck & Dice \u2013 After Work Modern - 19:00 Uhr",
    "start": "2026-04-21T19:00:00+02:00",
    "end": "2026-04-21T22:00:00+02:00",
    "location": "Deck & Dice Munich",
    "url": "https://www.dd-munich.de",
    "description": "",
    "all_day": false
  },
  {
    "title": "Deck & Dice \u2013 After Work Modern - 19:00 Uhr",
    "start": "2026-04-28T19:00:00+02:00",
    "end": "2026-04-28T22:00:00+02:00",
    "location": "Deck & Dice Munich",
    "url": "https://www.dd-munich.de",
    "description": "",
    "all_day": false
  },
  {
    "title": "Deck & Dice \u2013 After Work Modern - 19:00 Uhr",
    "start": "2026-05-05T19:00:00+02:00",
    "end": "2026-05-05T22:00:00+02:00",
    "location": "Deck & Dice Munich",
    "url": "https://www.dd-munich.de",
    "description": "",
    "all_day": false
  },
  {
    "title": "Deck & Dice \u2013 After Work Modern - 19:00 Uhr",
    "start": "2026-05-12T19:00:00+02:00",
    "end": "2026-05-12T22:00:00+02:00",
    "location": "Deck & Dice Munich",
    "url": "https://www.dd-munich.de",
    "description": "",
    "all_day": false
  },
  {
    "title": "Deck & Dice \u2013 After Work Modern - 19:00 Uhr",
    "start": "2026-05-19T19:00:00+02:00",
    "end": "2026-05-19T22:00:00+02:00",
    "location": "Deck & Dice Munich",
    "url": "https://www.dd-munich.de",
    "description": "",
    "all_day": false
  },
  {
    "title": "Deck & Dice \u2013 After Work Modern - 19:00 Uhr",
    "start": "2026-05-26T19:00:00+02:00",
    "end": "2026-05-26T22:00:00+02:00",
    "location": "Deck & Dice Munich",
    "url": "https://www.dd-munich.de",
    "description": "",
    "all_day": false
  },
  {
    "title": "Deck & Dice \u2013 After Work Modern - 19:00 Uhr",
    "start": "2026-06-02T19:00:00+02:00",
    "end": "2026-06-02T22:00:00+02:00",
    "location": "Deck & Dice Munich",
    "url": "https://www.dd-munich.de",
    "description": "",
    "all_day": false
  },
  {
    "title": "Deck & Dice \u2013 After Work Modern - 19:00 Uhr",
    "start": "2026-06-09T19:00:00+02:00",
    "end": "2026-06-09T22:00:00+02:00",
    "location": "Deck & Dice Munich",
    "url": "https://www.dd-munich.de",
    "description": "",
    "all_day": false
  },
  {
    "title": "Deck & Dice \u2013 After Work Modern - 19:00 Uhr",
    "start": "2026-06-16T19:00:00+02:00",
    "end": "2026-06-16T22:00:00+02:00",
    "location": "Deck & Dice Munich",
    "url": "https://www.dd-munich.de",
    "description": "",
    "all_day": false
  },
  {
    "title": "Deck & Dice \u2013 After Work Modern - 19:00 Uhr",
    "start": "2026-06-23T19:00:00+02:00",
    "end": "2026-06-23T22:00:00+02:00",
    "location": "Deck & Dice Munich",
    "url": "https://www.dd-munich.de",
    "description": "",
    "all_day": false
  },
  {
    "title": "Deck & Dice \u2013 After Work Modern - 19:00 Uhr",
    "start": "2026-06-30T19:00:00+02:00",
    "end": "2026-06-30T22:00:00+02:00",
    "location": "Deck & Dice Munich",
    "url": "https://www.dd-munich.de",
    "description": "",
    "all_day": false
  },
  {
    "title": "Deck & Dice \u2013 After Work Modern - 19:00 Uhr",
    "start": "2026-07-07T19:00:00+02:00",
    "end": "2026-07-07T22:00:00+02:00",
    "location": "Deck & Dice Munich",
    "url": "https://www.dd-munich.de",
    "description": "",
    "all_day": false
  },
  {
    "title": "Deck & Dice \u2013 After Work Modern - 19:00 Uhr",
    "start": "2026-07-14T19:00:00+02:00",
    "end": "2026-07-14T22:00:00+02:00",
    "location": "Deck & Dice Munich",
    "url": "https://www.dd-munich.de",
    "description": "",
    "all_day": false
  },
  {
    "title": "Deck & Dice \u2013 After Work Modern - 19:00 Uhr",
    "start": "2026-07-21T19:00:00+02:00",
    "end": "2026-07-21T22:00:00+02:00",
    "location": "Deck & Dice Munich",
    "url": "https://www.dd-munich.de",
    "description": "",
    "all_day": false
  },
  {
    "title": "Deck & Dice \u2013 After Work Modern - 19:00 Uhr",
    "start": "2026-07-28T19:00:00+02:00",
    "end": "2026-07-28T22:00:00+02:00",
    "location": "Deck & Dice Munich",
    "url": "https://www.dd-munich.de",
    "description": "",
    "all_day": false
  },
  {
    "title": "Deck & Dice \u2013 After Work Modern - 19:00 Uhr",
    "start": "2026-08-04T19:00:00+02:00",
    "end": "2026-08-04T22:00:00+02:00",
    "location": "Deck & Dice Munich",
    "url": "https://www.dd-munich.de",
    "description": "",
    "all_day": false
  },
  {
    "title": "Deck & Dice \u2013 After Work Modern - 19:00 Uhr",
    "start": "2026-08-11T19:00:00+02:00",
    "end": "2026-08-11T22:00:00+02:00",
    "location": "Deck & Dice Munich",
    "url": "https://www.dd-munich.de",
    "description": "",
    "all_day": false
  },
  {
    "title": "Deck & Dice \u2013 After Work Modern - 19:00 Uhr",
    "start": "2026-08-18T19:00:00+02:00",
    "end": "2026-08-18T22:00:00+02:00",
    "location": "Deck & Dice Munich",
    "url": "https://www.dd-munich.de",
    "description": "",
    "all_day": false
  },
  {
    "title": "Deck & Dice \u2013 After Work Modern - 19:00 Uhr",
    "start": "2026-08-25T19:00:00+02:00",
    "end": "2026-08-25T22:00:00+02:00",
    "location": "Deck & Dice Munich",
    "url": "https://www.dd-munich.de",
    "description": "",
    "all_day": false
  },
  {
    "title": "Deck & Dice \u2013 After Work Modern - 19:00 Uhr",
    "start": "2026-09-01T19:00:00+02:00",
    "end": "2026-09-01T22:00:00+02:00",
    "location": "Deck & Dice Munich",
    "url": "https://www.dd-munich.de",
    "description": "",
    "all_day": false
  },
  {
    "title": "Deck & Dice \u2013 After Work Modern - 19:00 Uhr",
    "start": "2026-09-08T19:00:00+02:00",
    "end": "2026-09-08T22:00:00+02:00",
    "location": "Deck & Dice Munich",
    "url": "https://www.dd-munich.de",
    "description": "",
    "all_day": false
  },
  {
    "title": "Deck & Dice \u2013 After Work Modern - 19:00 Uhr",
    "start": "2026-09-15T19:00:00+02:00",
    "end": "2026-09-15T22:00:00+02:00",
    "location": "Deck & Dice Munich",
    "url": "https://www.dd-munich.de",
    "description": "",
    "all_day": false
  },
  {
    "title": "Deck & Dice \u2013 After Work Modern - 19:00 Uhr",
    "start": "2026-09-22T19:00:00+02:00",
    "end": "2026-09-22T22:00:00+02:00",
    "location": "Deck & Dice Munich",
    "url": "https://www.dd-munich.de",
    "description": "",
    "all_day": false
  },
  {
    "title": "Deck & Dice \u2013 After Work Modern - 19:00 Uhr",
    "start": "2026-09-29T19:00:00+02:00",
    "end": "2026-09-29T22:00:00+02:00",
    "location": "Deck & Dice Munich",
    "url": "https://www.dd-munich.de",
    "description": "",
    "all_day": false
  },
  {
    "title": "Deck & Dice \u2013 After Work Modern - 19:00 Uhr",
    "start": "2026-10-06T19:00:00+02:00",
    "end": "2026-10-06T22:00:00+02:00",
    "location": "Deck & Dice Munich",
    "url": "https://www.dd-munich.de",
    "description": "",
    "all_day": false
  },
  {
    "title": "Deck & Dice \u2013 After Work Modern - 19:00 Uhr",
    "start": "2026-10-13T19:00:00+02:00",
    "end": "2026-10-13T22:00:00+02:00",
    "location": "Deck & Dice Munich",
    "url": "https://www.dd-munich.de",
    "description": "",
    "all_day": false
  },
  {
    "title": "Deck & Dice \u2013 After Work Modern - 19:00 Uhr",
    "start": "2026-10-20T19:00:00+02:00",
    "end": "2026-10-20T22:00:00+02:00",
    "location": "Deck & Dice Munich",
    "url": "https://www.dd-munich.de",
    "description": "",
    "all_day": false
  },
  {
    "title": "Deck & Dice \u2013 After Work Modern - 19:00 Uhr",
    "start": "2026-10-27T19:00:00+01:00",
    "end": "2026-10-27T22:00:00+01:00",
    "location": "Deck & Dice Munich",
    "url": "https://www.dd-munich.de",
    "description": "",
    "all_day": false
  },
  {
    "title": "Deck & Dice \u2013 After Work Modern - 19:00 Uhr",
    "start": "2026-11-03T19:00:00+01:00",
    "end": "2026-11-03T22:00:00+01:00",
    "location": "Deck & Dice Munich",
    "url": "https://www.dd-munich.de",
    "description": "",
    "all_day": false
  },
  {
    "title": "Deck & Dice \u2013 After Work Modern - 19:00 Uhr",
    "start": "2026-11-10T19:00:00+01:00",
    "end": "2026-11-10T22:00:00+01:00",
    "location": "Deck & Dice Munich",
    "url": "https://www.dd-munich.de",
    "description": "",
    "all_day": false
  },
  {
    "title": "Deck & Dice \u2013 After Work Modern - 19:00 Uhr",
    "start": "2026-11-17T19:00:00+01:00",
    "end": "2026-11-17T22:00:00+01:00",
    "location": "Deck & Dice Munich",
    "url": "https://www.dd-munich.de",
    "description": "",
    "all_day": false
  },
  {
    "title": "Deck & Dice \u2013 After Work Modern - 19:00 Uhr",
    "start": "2026-11-24T19:00:00+01:00",
    "end": "2026-11-24T22:00:00+01:00",
    "location": "Deck & Dice Munich",
    "url": "https://www.dd-munich.de",
    "description": "",
    "all_day": false
  },
  {
    "title": "Deck & Dice \u2013 After Work Modern - 19:00 Uhr",
    "start": "2026-12-01T19:00:00+01:00",
    "end": "2026-12-01T22:00:00+01:00",
    "location": "Deck & Dice Munich",
    "url": "https://www.dd-munich.de",
    "description": "",
    "all_day": false
  },
  {
    "title": "Deck & Dice \u2013 After Work Modern - 19:00 Uhr",
    "start": "2026-12-08T19:00:00+01:00",
    "end": "2026-12-08T22:00:00+01:00",
    "location": "Deck & Dice Munich",
    "url": "https://www.dd-munich.de",
    "description": "",
    "all_day": false
  },
  {
    "title": "Deck & Dice \u2013 After Work Modern - 19:00 Uhr",
    "start": "2026-12-15T19:00:00+01:00",
    "end": "2026-12-15T22:00:00+01:00",
    "location": "Deck & Dice Munich",
    "url": "https://www.dd-munich.de",
    "description": "",
    "all_day": false
  },
  {
    "title": "Deck & Dice \u2013 After Work Modern - 19:00 Uhr",
    "start": "2026-12-22T19:00:00+01:00",
    "end": "2026-12-22T22:00:00+01:00",
    "location": "Deck & Dice Munich",
    "url": "https://www.dd-munich.de",
    "description": "",
    "all_day": false
  },
  {
    "title": "Deck & Dice \u2013 After Work Modern - 19:00 Uhr",
    "start": "2026-12-29T19:00:00+01:00",
    "end": "2026-12-29T22:00:00+01:00",
    "location": "Deck & Dice Munich",
    "url": "https://www.dd-munich.de",
    "description": "",
    "all_day": false
  },
  {
    "title": "Deck & Dice \u2013 After Work Legacy",
    "start": "2026-04-01T19:00:00+02:00",
    "end": "2026-04-01T22:00:00+02:00",
    "location": "Deck & Dice Munich",
    "url": "https://www.dd-munich.de",
    "description": "",
    "all_day": false
  },
  {
    "title": "Deck & Dice \u2013 After Work Legacy",
    "start": "2026-04-08T19:00:00+02:00",
    "end": "2026-04-08T22:00:00+02:00",
    "location": "Deck & Dice Munich",
    "url": "https://www.dd-munich.de",
    "description": "",
    "all_day": false
  },
  {
    "title": "Deck & Dice \u2013 After Work Legacy",
    "start": "2026-04-15T19:00:00+02:00",
    "end": "2026-04-15T22:00:00+02:00",
    "location": "Deck & Dice Munich",
    "url": "https://www.dd-munich.de",
    "description": "",
    "all_day": false
  },
  {
    "title": "Deck & Dice \u2013 After Work Legacy",
    "start": "2026-04-22T19:00:00+02:00",
    "end": "2026-04-22T22:00:00+02:00",
    "location": "Deck & Dice Munich",
    "url": "https://www.dd-munich.de",
    "description": "",
    "all_day": false
  },
  {
    "title": "Deck & Dice \u2013 After Work Legacy",
    "start": "2026-04-29T19:00:00+02:00",
    "end": "2026-04-29T22:00:00+02:00",
    "location": "Deck & Dice Munich",
    "url": "https://www.dd-munich.de",
    "description": "",
    "all_day": false
  },
  {
    "title": "Deck & Dice \u2013 After Work Legacy",
    "start": "2026-05-06T19:00:00+02:00",
    "end": "2026-05-06T22:00:00+02:00",
    "location": "Deck & Dice Munich",
    "url": "https://www.dd-munich.de",
    "description": "",
    "all_day": false
  },
  {
    "title": "Deck & Dice \u2013 After Work Legacy",
    "start": "2026-05-13T19:00:00+02:00",
    "end": "2026-05-13T22:00:00+02:00",
    "location": "Deck & Dice Munich",
    "url": "https://www.dd-munich.de",
    "description": "",
    "all_day": false
  },
  {
    "title": "Deck & Dice \u2013 After Work Legacy",
    "start": "2026-05-20T19:00:00+02:00",
    "end": "2026-05-20T22:00:00+02:00",
    "location": "Deck & Dice Munich",
    "url": "https://www.dd-munich.de",
    "description": "",
    "all_day": false
  },
  {
    "title": "Deck & Dice \u2013 After Work Legacy",
    "start": "2026-05-27T19:00:00+02:00",
    "end": "2026-05-27T22:00:00+02:00",
    "location": "Deck & Dice Munich",
    "url": "https://www.dd-munich.de",
    "description": "",
    "all_day": false
  },
  {
    "title": "Deck & Dice \u2013 After Work Legacy",
    "start": "2026-06-03T19:00:00+02:00",
    "end": "2026-06-03T22:00:00+02:00",
    "location": "Deck & Dice Munich",
    "url": "https://www.dd-munich.de",
    "description": "",
    "all_day": false
  },
  {
    "title": "Deck & Dice \u2013 After Work Legacy",
    "start": "2026-06-10T19:00:00+02:00",
    "end": "2026-06-10T22:00:00+02:00",
    "location": "Deck & Dice Munich",
    "url": "https://www.dd-munich.de",
    "description": "",
    "all_day": false
  },
  {
    "title": "Deck & Dice \u2013 After Work Legacy",
    "start": "2026-06-17T19:00:00+02:00",
    "end": "2026-06-17T22:00:00+02:00",
    "location": "Deck & Dice Munich",
    "url": "https://www.dd-munich.de",
    "description": "",
    "all_day": false
  },
  {
    "title": "Deck & Dice \u2013 After Work Legacy",
    "start": "2026-06-24T19:00:00+02:00",
    "end": "2026-06-24T22:00:00+02:00",
    "location": "Deck & Dice Munich",
    "url": "https://www.dd-munich.de",
    "description": "",
    "all_day": false
  },
  {
    "title": "Deck & Dice \u2013 After Work Legacy",
    "start": "2026-07-01T19:00:00+02:00",
    "end": "2026-07-01T22:00:00+02:00",
    "location": "Deck & Dice Munich",
    "url": "https://www.dd-munich.de",
    "description": "",
    "all_day": false
  },
  {
    "title": "Deck & Dice \u2013 After Work Legacy",
    "start": "2026-07-08T19:00:00+02:00",
    "end": "2026-07-08T22:00:00+02:00",
    "location": "Deck & Dice Munich",
    "url": "https://www.dd-munich.de",
    "description": "",
    "all_day": false
  },
  {
    "title": "Deck & Dice \u2013 After Work Legacy",
    "start": "2026-07-15T19:00:00+02:00",
    "end": "2026-07-15T22:00:00+02:00",
    "location": "Deck & Dice Munich",
    "url": "https://www.dd-munich.de",
    "description": "",
    "all_day": false
  },
  {
    "title": "Deck & Dice \u2013 After Work Legacy",
    "start": "2026-07-22T19:00:00+02:00",
    "end": "2026-07-22T22:00:00+02:00",
    "location": "Deck & Dice Munich",
    "url": "https://www.dd-munich.de",
    "description": "",
    "all_day": false
  },
  {
    "title": "Deck & Dice \u2013 After Work Legacy",
    "start": "2026-07-29T19:00:00+02:00",
    "end": "2026-07-29T22:00:00+02:00",
    "location": "Deck & Dice Munich",
    "url": "https://www.dd-munich.de",
    "description": "",
    "all_day": false
  },
  {
    "title": "Deck & Dice \u2013 After Work Legacy",
    "start": "2026-08-05T19:00:00+02:00",
    "end": "2026-08-05T22:00:00+02:00",
    "location": "Deck & Dice Munich",
    "url": "https://www.dd-munich.de",
    "description": "",
    "all_day": false
  },
  {
    "title": "Deck & Dice \u2013 After Work Legacy",
    "start": "2026-08-12T19:00:00+02:00",
    "end": "2026-08-12T22:00:00+02:00",
    "location": "Deck & Dice Munich",
    "url": "https://www.dd-munich.de",
    "description": "",
    "all_day": false
  },
  {
    "title": "Deck & Dice \u2013 After Work Legacy",
    "start": "2026-08-19T19:00:00+02:00",
    "end": "2026-08-19T22:00:00+02:00",
    "location": "Deck & Dice Munich",
    "url": "https://www.dd-munich.de",
    "description": "",
    "all_day": false
  },
  {
    "title": "Deck & Dice \u2013 After Work Legacy",
    "start": "2026-08-26T19:00:00+02:00",
    "end": "2026-08-26T22:00:00+02:00",
    "location": "Deck & Dice Munich",
    "url": "https://www.dd-munich.de",
    "description": "",
    "all_day": false
  },
  {
    "title": "Deck & Dice \u2013 After Work Legacy",
    "start": "2026-09-02T19:00:00+02:00",
    "end": "2026-09-02T22:00:00+02:00",
    "location": "Deck & Dice Munich",
    "url": "https://www.dd-munich.de",
    "description": "",
    "all_day": false
  },
  {
    "title": "Deck & Dice \u2013 After Work Legacy",
    "start": "2026-09-09T19:00:00+02:00",
    "end": "2026-09-09T22:00:00+02:00",
    "location": "Deck & Dice Munich",
    "url": "https://www.dd-munich.de",
    "description": "",
    "all_day": false
  },
  {
    "title": "Deck & Dice \u2013 After Work Legacy",
    "start": "2026-09-16T19:00:00+02:00",
    "end": "2026-09-16T22:00:00+02:00",
    "location": "Deck & Dice Munich",
    "url": "https://www.dd-munich.de",
    "description": "",
    "all_day": false
  },
  {
    "title": "Deck & Dice \u2013 After Work Legacy",
    "start": "2026-09-23T19:00:00+02:00",
    "end": "2026-09-23T22:00:00+02:00",
    "location": "Deck & Dice Munich",
    "url": "https://www.dd-munich.de",
    "description": "",
    "all_day": false
  },
  {
    "title": "Deck & Dice \u2013 After Work Legacy",
    "start": "2026-09-30T19:00:00+02:00",
    "end": "2026-09-30T22:00:00+02:00",
    "location": "Deck & Dice Munich",
    "url": "https://www.dd-munich.de",
    "description": "",
    "all_day": false
  },
  {
    "title": "Deck & Dice \u2013 After Work Legacy",
    "start": "2026-10-07T19:00:00+02:00",
    "end": "2026-10-07T22:00:00+02:00",
    "location": "Deck & Dice Munich",
    "url": "https://www.dd-munich.de",
    "description": "",
    "all_day": false
  },
  {
    "title": "Deck & Dice \u2013 After Work Legacy",
    "start": "2026-10-14T19:00:00+02:00",
    "end": "2026-10-14T22:00:00+02:00",
    "location": "Deck & Dice Munich",
    "url": "https://www.dd-munich.de",
    "description": "",
    "all_day": false
  },
  {
    "title": "Deck & Dice \u2013 After Work Legacy",
    "start": "2026-10-21T19:00:00+02:00",
    "end": "2026-10-21T22:00:00+02:00",
    "location": "Deck & Dice Munich",
    "url": "https://www.dd-munich.de",
    "description": "",
    "all_day": false
  },
  {
    "title": "Deck & Dice \u2013 After Work Legacy",
    "start": "2026-10-28T19:00:00+01:00",
    "end": "2026-10-28T22:00:00+01:00",
    "location": "Deck & Dice Munich",
    "url": "https://www.dd-munich.de",
    "description": "",
    "all_day": false
  },
  {
    "title": "Deck & Dice \u2013 After Work Legacy",
    "start": "2026-11-04T19:00:00+01:00",
    "end": "2026-11-04T22:00:00+01:00",
    "location": "Deck & Dice Munich",
    "url": "https://www.dd-munich.de",
    "description": "",
    "all_day": false
  },
  {
    "title": "Deck & Dice \u2013 After Work Legacy",
    "start": "2026-11-11T19:00:00+01:00",
    "end": "2026-11-11T22:00:00+01:00",
    "location": "Deck & Dice Munich",
    "url": "https://www.dd-munich.de",
    "description": "",
    "all_day": false
  },
  {
    "title": "Deck & Dice \u2013 After Work Legacy",
    "start": "2026-11-18T19:00:00+01:00",
    "end": "2026-11-18T22:00:00+01:00",
    "location": "Deck & Dice Munich",
    "url": "https://www.dd-munich.de",
    "description": "",
    "all_day": false
  },
  {
    "title": "Deck & Dice \u2013 After Work Legacy",
    "start": "2026-11-25T19:00:00+01:00",
    "end": "2026-11-25T22:00:00+01:00",
    "location": "Deck & Dice Munich",
    "url": "https://www.dd-munich.de",
    "description": "",
    "all_day": false
  },
  {
    "title": "Deck & Dice \u2013 After Work Legacy",
    "start": "2026-12-02T19:00:00+01:00",
    "end": "2026-12-02T22:00:00+01:00",
    "location": "Deck & Dice Munich",
    "url": "https://www.dd-munich.de",
    "description": "",
    "all_day": false
  },
  {
    "title": "Deck & Dice \u2013 After Work Legacy",
    "start": "2026-12-09T19:00:00+01:00",
    "end": "2026-12-09T22:00:00+01:00",
    "location": "Deck & Dice Munich",
    "url": "https://www.dd-munich.de",
    "description": "",
    "all_day": false
  },
  {
    "title": "Deck & Dice \u2013 After Work Legacy",
    "start": "2026-12-16T19:00:00+01:00",
    "end": "2026-12-16T22:00:00+01:00",
    "location": "Deck & Dice Munich",
    "url": "https://www.dd-munich.de",
    "description": "",
    "all_day": false
  },
  {
    "title": "Deck & Dice \u2013 After Work Legacy",
    "start": "2026-12-23T19:00:00+01:00",
    "end": "2026-12-23T22:00:00+01:00",
    "location": "Deck & Dice Munich",
    "url": "https://www.dd-munich.de",
    "description": "",
    "all_day": false
  },
  {
    "title": "Deck & Dice \u2013 After Work Legacy",
    "start": "2026-12-30T19:00:00+01:00",
    "end": "2026-12-30T22:00:00+01:00",
    "location": "Deck & Dice Munich",
    "url": "https://www.dd-munich.de",
    "description": "",
    "all_day": false
  },
  {
    "title": "Deck & Dice \u2013 After Work Premodern 19:00 Uhr",
    "start": "2026-04-02T19:00:00+02:00",
    "end": "2026-04-02T22:00:00+02:00",
    "location": "Deck & Dice Munich",
    "url": "https://www.dd-munich.de",
    "description": "",
    "all_day": false
  },
  {
    "title": "Deck & Dice \u2013 After Work Premodern 19:00 Uhr",
    "start": "2026-04-09T19:00:00+02:00",
    "end": "2026-04-09T22:00:00+02:00",
    "location": "Deck & Dice Munich",
    "url": "https://www.dd-munich.de",
    "description": "",
    "all_day": false
  },
  {
    "title": "Deck & Dice \u2013 After Work Premodern 19:00 Uhr",
    "start": "2026-04-16T19:00:00+02:00",
    "end": "2026-04-16T22:00:00+02:00",
    "location": "Deck & Dice Munich",
    "url": "https://www.dd-munich.de",
    "description": "",
    "all_day": false
  },
  {
    "title": "Deck & Dice \u2013 After Work Premodern 19:00 Uhr",
    "start": "2026-04-23T19:00:00+02:00",
    "end": "2026-04-23T22:00:00+02:00",
    "location": "Deck & Dice Munich",
    "url": "https://www.dd-munich.de",
    "description": "",
    "all_day": false
  },
  {
    "title": "Deck & Dice \u2013 After Work Premodern 19:00 Uhr",
    "start": "2026-04-30T19:00:00+02:00",
    "end": "2026-04-30T22:00:00+02:00",
    "location": "Deck & Dice Munich",
    "url": "https://www.dd-munich.de",
    "description": "",
    "all_day": false
  },
  {
    "title": "Deck & Dice \u2013 After Work Premodern 19:00 Uhr",
    "start": "2026-05-07T19:00:00+02:00",
    "end": "2026-05-07T22:00:00+02:00",
    "location": "Deck & Dice Munich",
    "url": "https://www.dd-munich.de",
    "description": "",
    "all_day": false
  },
  {
    "title": "Deck & Dice \u2013 After Work Premodern 19:00 Uhr",
    "start": "2026-05-21T19:00:00+02:00",
    "end": "2026-05-21T22:00:00+02:00",
    "location": "Deck & Dice Munich",
    "url": "https://www.dd-munich.de",
    "description": "",
    "all_day": false
  },
  {
    "title": "Deck & Dice \u2013 After Work Premodern 19:00 Uhr",
    "start": "2026-05-28T19:00:00+02:00",
    "end": "2026-05-28T22:00:00+02:00",
    "location": "Deck & Dice Munich",
    "url": "https://www.dd-munich.de",
    "description": "",
    "all_day": false
  },
  {
    "title": "Deck & Dice \u2013 After Work Premodern 19:00 Uhr",
    "start": "2026-06-11T19:00:00+02:00",
    "end": "2026-06-11T22:00:00+02:00",
    "location": "Deck & Dice Munich",
    "url": "https://www.dd-munich.de",
    "description": "",
    "all_day": false
  },
  {
    "title": "Deck & Dice \u2013 After Work Premodern 19:00 Uhr",
    "start": "2026-06-18T19:00:00+02:00",
    "end": "2026-06-18T22:00:00+02:00",
    "location": "Deck & Dice Munich",
    "url": "https://www.dd-munich.de",
    "description": "",
    "all_day": false
  },
  {
    "title": "Deck & Dice \u2013 After Work Premodern 19:00 Uhr",
    "start": "2026-06-25T19:00:00+02:00",
    "end": "2026-06-25T22:00:00+02:00",
    "location": "Deck & Dice Munich",
    "url": "https://www.dd-munich.de",
    "description": "",
    "all_day": false
  },
  {
    "title": "Deck & Dice \u2013 After Work Premodern 19:00 Uhr",
    "start": "2026-07-02T19:00:00+02:00",
    "end": "2026-07-02T22:00:00+02:00",
    "location": "Deck & Dice Munich",
    "url": "https://www.dd-munich.de",
    "description": "",
    "all_day": false
  },
  {
    "title": "Deck & Dice \u2013 After Work Premodern 19:00 Uhr",
    "start": "2026-07-09T19:00:00+02:00",
    "end": "2026-07-09T22:00:00+02:00",
    "location": "Deck & Dice Munich",
    "url": "https://www.dd-munich.de",
    "description": "",
    "all_day": false
  },
  {
    "title": "Deck & Dice \u2013 After Work Premodern 19:00 Uhr",
    "start": "2026-07-16T19:00:00+02:00",
    "end": "2026-07-16T22:00:00+02:00",
    "location": "Deck & Dice Munich",
    "url": "https://www.dd-munich.de",
    "description": "",
    "all_day": false
  },
  {
    "title": "Deck & Dice \u2013 After Work Premodern 19:00 Uhr",
    "start": "2026-07-23T19:00:00+02:00",
    "end": "2026-07-23T22:00:00+02:00",
    "location": "Deck & Dice Munich",
    "url": "https://www.dd-munich.de",
    "description": "",
    "all_day": false
  },
  {
    "title": "Deck & Dice \u2013 After Work Premodern 19:00 Uhr",
    "start": "2026-07-30T19:00:00+02:00",
    "end": "2026-07-30T22:00:00+02:00",
    "location": "Deck & Dice Munich",
    "url": "https://www.dd-munich.de",
    "description": "",
    "all_day": false
  },
  {
    "title": "Deck & Dice \u2013 After Work Premodern 19:00 Uhr",
    "start": "2026-08-06T19:00:00+02:00",
    "end": "2026-08-06T22:00:00+02:00",
    "location": "Deck & Dice Munich",
    "url": "https://www.dd-munich.de",
    "description": "",
    "all_day": false
  },
  {
    "title": "Deck & Dice \u2013 After Work Premodern 19:00 Uhr",
    "start": "2026-08-13T19:00:00+02:00",
    "end": "2026-08-13T22:00:00+02:00",
    "location": "Deck & Dice Munich",
    "url": "https://www.dd-munich.de",
    "description": "",
    "all_day": false
  },
  {
    "title": "Deck & Dice \u2013 After Work Premodern 19:00 Uhr",
    "start": "2026-08-20T19:00:00+02:00",
    "end": "2026-08-20T22:00:00+02:00",
    "location": "Deck & Dice Munich",
    "url": "https://www.dd-munich.de",
    "description": "",
    "all_day": false
  },
  {
    "title": "Deck & Dice \u2013 After Work Premodern 19:00 Uhr",
    "start": "2026-08-27T19:00:00+02:00",
    "end": "2026-08-27T22:00:00+02:00",
    "location": "Deck & Dice Munich",
    "url": "https://www.dd-munich.de",
    "description": "",
    "all_day": false
  },
  {
    "title": "Deck & Dice \u2013 After Work Premodern 19:00 Uhr",
    "start": "2026-09-03T19:00:00+02:00",
    "end": "2026-09-03T22:00:00+02:00",
    "location": "Deck & Dice Munich",
    "url": "https://www.dd-munich.de",
    "description": "",
    "all_day": false
  },
  {
    "title": "Deck & Dice \u2013 After Work Premodern 19:00 Uhr",
    "start": "2026-09-10T19:00:00+02:00",
    "end": "2026-09-10T22:00:00+02:00",
    "location": "Deck & Dice Munich",
    "url": "https://www.dd-munich.de",
    "description": "",
    "all_day": false
  },
  {
    "title": "Deck & Dice \u2013 After Work Premodern 19:00 Uhr",
    "start": "2026-09-17T19:00:00+02:00",
    "end": "2026-09-17T22:00:00+02:00",
    "location": "Deck & Dice Munich",
    "url": "https://www.dd-munich.de",
    "description": "",
    "all_day": false
  },
  {
    "title": "Deck & Dice \u2013 After Work Premodern 19:00 Uhr",
    "start": "2026-09-24T19:00:00+02:00",
    "end": "2026-09-24T22:00:00+02:00",
    "location": "Deck & Dice Munich",
    "url": "https://www.dd-munich.de",
    "description": "",
    "all_day": false
  },
  {
    "title": "Deck & Dice \u2013 After Work Premodern 19:00 Uhr",
    "start": "2026-10-01T19:00:00+02:00",
    "end": "2026-10-01T22:00:00+02:00",
    "location": "Deck & Dice Munich",
    "url": "https://www.dd-munich.de",
    "description": "",
    "all_day": false
  },
  {
    "title": "Deck & Dice \u2013 After Work Premodern 19:00 Uhr",
    "start": "2026-10-08T19:00:00+02:00",
    "end": "2026-10-08T22:00:00+02:00",
    "location": "Deck & Dice Munich",
    "url": "https://www.dd-munich.de",
    "description": "",
    "all_day": false
  },
  {
    "title": "Deck & Dice \u2013 After Work Premodern 19:00 Uhr",
    "start": "2026-10-15T19:00:00+02:00",
    "end": "2026-10-15T22:00:00+02:00",
    "location": "Deck & Dice Munich",
    "url": "https://www.dd-munich.de",
    "description": "",
    "all_day": false
  },
  {
    "title": "Deck & Dice \u2013 After Work Premodern 19:00 Uhr",
    "start": "2026-10-22T19:00:00+02:00",
    "end": "2026-10-22T22:00:00+02:00",
    "location": "Deck & Dice Munich",
    "url": "https://www.dd-munich.de",
    "description": "",
    "all_day": false
  },
  {
    "title": "Deck & Dice \u2013 After Work Premodern 19:00 Uhr",
    "start": "2026-10-29T19:00:00+01:00",
    "end": "2026-10-29T22:00:00+01:00",
    "location": "Deck & Dice Munich",
    "url": "https://www.dd-munich.de",
    "description": "",
    "all_day": false
  },
  {
    "title": "Deck & Dice \u2013 After Work Premodern 19:00 Uhr",
    "start": "2026-11-05T19:00:00+01:00",
    "end": "2026-11-05T22:00:00+01:00",
    "location": "Deck & Dice Munich",
    "url": "https://www.dd-munich.de",
    "description": "",
    "all_day": false
  },
  {
    "title": "Deck & Dice \u2013 After Work Premodern 19:00 Uhr",
    "start": "2026-11-12T19:00:00+01:00",
    "end": "2026-11-12T22:00:00+01:00",
    "location": "Deck & Dice Munich",
    "url": "https://www.dd-munich.de",
    "description": "",
    "all_day": false
  },
  {
    "title": "Deck & Dice \u2013 After Work Premodern 19:00 Uhr",
    "start": "2026-11-19T19:00:00+01:00",
    "end": "2026-11-19T22:00:00+01:00",
    "location": "Deck & Dice Munich",
    "url": "https://www.dd-munich.de",
    "description": "",
    "all_day": false
  },
  {
    "title": "Deck & Dice \u2013 After Work Premodern 19:00 Uhr",
    "start": "2026-11-26T19:00:00+01:00",
    "end": "2026-11-26T22:00:00+01:00",
    "location": "Deck & Dice Munich",
    "url": "https://www.dd-munich.de",
    "description": "",
    "all_day": false
  },
  {
    "title": "Deck & Dice \u2013 After Work Premodern 19:00 Uhr",
    "start": "2026-12-03T19:00:00+01:00",
    "end": "2026-12-03T22:00:00+01:00",
    "location": "Deck & Dice Munich",
    "url": "https://www.dd-munich.de",
    "description": "",
    "all_day": false
  },
  {
    "title": "Deck & Dice \u2013 After Work Premodern 19:00 Uhr",
    "start": "2026-12-10T19:00:00+01:00",
    "end": "2026-12-10T22:00:00+01:00",
    "location": "Deck & Dice Munich",
    "url": "https://www.dd-munich.de",
    "description": "",
    "all_day": false
  },
  {
    "title": "Deck & Dice \u2013 After Work Premodern 19:00 Uhr",
    "start": "2026-12-17T19:00:00+01:00",
    "end": "2026-12-17T22:00:00+01:00",
    "location": "Deck & Dice Munich",
    "url": "https://www.dd-munich.de",
    "description": "",
    "all_day": false
  },
  {
    "title": "Deck & Dice \u2013 After Work Premodern 19:00 Uhr",
    "start": "2026-12-24T19:00:00+01:00",
    "end": "2026-12-24T22:00:00+01:00",
    "location": "Deck & Dice Munich",
    "url": "https://www.dd-munich.de",
    "description": "",
    "all_day": false
  },
  {
    "title": "Deck & Dice \u2013 Friday Night Standard 18.30",
    "start": "2026-04-10T18:30:00+02:00",
    "end": "2026-04-10T21:30:00+02:00",
    "location": "Deck & Dice Munich",
    "url": "https://www.dd-munich.de",
    "description": "",
    "all_day": false
  },
  {
    "title": "Deck & Dice \u2013 Friday Night Standard 18.30",
    "start": "2026-04-17T18:30:00+02:00",
    "end": "2026-04-17T21:30:00+02:00",
    "location": "Deck & Dice Munich",
    "url": "https://www.dd-munich.de",
    "description": "",
    "all_day": false
  },
  {
    "title": "Deck & Dice \u2013 Friday Night Standard 18.30",
    "start": "2026-04-24T18:30:00+02:00",
    "end": "2026-04-24T21:30:00+02:00",
    "location": "Deck & Dice Munich",
    "url": "https://www.dd-munich.de",
    "description": "",
    "all_day": false
  },
  {
    "title": "Deck & Dice \u2013 Friday Night Standard 18.30",
    "start": "2026-05-08T18:30:00+02:00",
    "end": "2026-05-08T21:30:00+02:00",
    "location": "Deck & Dice Munich",
    "url": "https://www.dd-munich.de",
    "description": "",
    "all_day": false
  },
  {
    "title": "Deck & Dice \u2013 Friday Night Standard 18.30",
    "start": "2026-05-15T18:30:00+02:00",
    "end": "2026-05-15T21:30:00+02:00",
    "location": "Deck & Dice Munich",
    "url": "https://www.dd-munich.de",
    "description": "",
    "all_day": false
  },
  {
    "title": "Deck & Dice \u2013 Friday Night Standard 18.30",
    "start": "2026-05-22T18:30:00+02:00",
    "end": "2026-05-22T21:30:00+02:00",
    "location": "Deck & Dice Munich",
    "url": "https://www.dd-munich.de",
    "description": "",
    "all_day": false
  },
  {
    "title": "Deck & Dice \u2013 Friday Night Standard 18.30",
    "start": "2026-05-29T18:30:00+02:00",
    "end": "2026-05-29T21:30:00+02:00",
    "location": "Deck & Dice Munich",
    "url": "https://www.dd-munich.de",
    "description": "",
    "all_day": false
  },
  {
    "title": "Deck & Dice \u2013 Friday Night Standard 18.30",
    "start": "2026-06-05T18:30:00+02:00",
    "end": "2026-06-05T21:30:00+02:00",
    "location": "Deck & Dice Munich",
    "url": "https://www.dd-munich.de",
    "description": "",
    "all_day": false
  },
  {
    "title": "Deck & Dice \u2013 Friday Night Standard 18.30",
    "start": "2026-06-12T18:30:00+02:00",
    "end": "2026-06-12T21:30:00+02:00",
    "location": "Deck & Dice Munich",
    "url": "https://www.dd-munich.de",
    "description": "",
    "all_day": false
  },
  {
    "title": "Deck & Dice \u2013 Friday Night Standard 18.30",
    "start": "2026-06-19T18:30:00+02:00",
    "end": "2026-06-19T21:30:00+02:00",
    "location": "Deck & Dice Munich",
    "url": "https://www.dd-munich.de",
    "description": "",
    "all_day": false
  },
  {
    "title": "Deck & Dice \u2013 Friday Night Standard 18.30",
    "start": "2026-06-26T18:30:00+02:00",
    "end": "2026-06-26T21:30:00+02:00",
    "location": "Deck & Dice Munich",
    "url": "https://www.dd-munich.de",
    "description": "",
    "all_day": false
  },
  {
    "title": "Deck & Dice \u2013 Friday Night Standard 18.30",
    "start": "2026-07-03T18:30:00+02:00",
    "end": "2026-07-03T21:30:00+02:00",
    "location": "Deck & Dice Munich",
    "url": "https://www.dd-munich.de",
    "description": "",
    "all_day": false
  },
  {
    "title": "Deck & Dice \u2013 Friday Night Standard 18.30",
    "start": "2026-07-10T18:30:00+02:00",
    "end": "2026-07-10T21:30:00+02:00",
    "location": "Deck & Dice Munich",
    "url": "https://www.dd-munich.de",
    "description": "",
    "all_day": false
  },
  {
    "title": "Deck & Dice \u2013 Friday Night Standard 18.30",
    "start": "2026-07-17T18:30:00+02:00",
    "end": "2026-07-17T21:30:00+02:00",
    "location": "Deck & Dice Munich",
    "url": "https://www.dd-munich.de",
    "description": "",
    "all_day": false
  },
  {
    "title": "Deck & Dice \u2013 Friday Night Standard 18.30",
    "start": "2026-07-24T18:30:00+02:00",
    "end": "2026-07-24T21:30:00+02:00",
    "location": "Deck & Dice Munich",
    "url": "https://www.dd-munich.de",
    "description": "",
    "all_day": false
  },
  {
    "title": "Deck & Dice \u2013 Friday Night Standard 18.30",
    "start": "2026-07-31T18:30:00+02:00",
    "end": "2026-07-31T21:30:00+02:00",
    "location": "Deck & Dice Munich",
    "url": "https://www.dd-munich.de",
    "description": "",
    "all_day": false
  },
  {
    "title": "Deck & Dice \u2013 Friday Night Standard 18.30",
    "start": "2026-08-07T18:30:00+02:00",
    "end": "2026-08-07T21:30:00+02:00",
    "location": "Deck & Dice Munich",
    "url": "https://www.dd-munich.de",
    "description": "",
    "all_day": false
  },
  {
    "title": "Deck & Dice \u2013 Friday Night Standard 18.30",
    "start": "2026-08-14T18:30:00+02:00",
    "end": "2026-08-14T21:30:00+02:00",
    "location": "Deck & Dice Munich",
    "url": "https://www.dd-munich.de",
    "description": "",
    "all_day": false
  },
  {
    "title": "Deck & Dice \u2013 Friday Night Standard 18.30",
    "start": "2026-08-21T18:30:00+02:00",
    "end": "2026-08-21T21:30:00+02:00",
    "location": "Deck & Dice Munich",
    "url": "https://www.dd-munich.de",
    "description": "",
    "all_day": false
  },
  {
    "title": "Deck & Dice \u2013 Friday Night Standard 18.30",
    "start": "2026-08-28T18:30:00+02:00",
    "end": "2026-08-28T21:30:00+02:00",
    "location": "Deck & Dice Munich",
    "url": "https://www.dd-munich.de",
    "description": "",
    "all_day": false
  },
  {
    "title": "Deck & Dice \u2013 Friday Night Standard 18.30",
    "start": "2026-09-04T18:30:00+02:00",
    "end": "2026-09-04T21:30:00+02:00",
    "location": "Deck & Dice Munich",
    "url": "https://www.dd-munich.de",
    "description": "",
    "all_day": false
  },
  {
    "title": "Deck & Dice \u2013 Friday Night Standard 18.30",
    "start": "2026-09-11T18:30:00+02:00",
    "end": "2026-09-11T21:30:00+02:00",
    "location": "Deck & Dice Munich",
    "url": "https://www.dd-munich.de",
    "description": "",
    "all_day": false
  },
  {
    "title": "Deck & Dice \u2013 Friday Night Standard 18.30",
    "start": "2026-09-18T18:30:00+02:00",
    "end": "2026-09-18T21:30:00+02:00",
    "location": "Deck & Dice Munich",
    "url": "https://www.dd-munich.de",
    "description": "",
    "all_day": false
  },
  {
    "title": "Deck & Dice \u2013 Friday Night Standard 18.30",
    "start": "2026-09-25T18:30:00+02:00",
    "end": "2026-09-25T21:30:00+02:00",
    "location": "Deck & Dice Munich",
    "url": "https://www.dd-munich.de",
    "description": "",
    "all_day": false
  },
  {
    "title": "Deck & Dice \u2013 Friday Night Standard 18.30",
    "start": "2026-10-02T18:30:00+02:00",
    "end": "2026-10-02T21:30:00+02:00",
    "location": "Deck & Dice Munich",
    "url": "https://www.dd-munich.de",
    "description": "",
    "all_day": false
  },
  {
    "title": "Deck & Dice \u2013 Friday Night Standard 18.30",
    "start": "2026-10-09T18:30:00+02:00",
    "end": "2026-10-09T21:30:00+02:00",
    "location": "Deck & Dice Munich",
    "url": "https://www.dd-munich.de",
    "description": "",
    "all_day": false
  },
  {
    "title": "Deck & Dice \u2013 Friday Night Standard 18.30",
    "start": "2026-10-16T18:30:00+02:00",
    "end": "2026-10-16T21:30:00+02:00",
    "location": "Deck & Dice Munich",
    "url": "https://www.dd-munich.de",
    "description": "",
    "all_day": false
  },
  {
    "title": "Deck & Dice \u2013 Friday Night Standard 18.30",
    "start": "2026-10-23T18:30:00+02:00",
    "end": "2026-10-23T21:30:00+02:00",
    "location": "Deck & Dice Munich",
    "url": "https://www.dd-munich.de",
    "description": "",
    "all_day": false
  },
  {
    "title": "Deck & Dice \u2013 Friday Night Standard 18.30",
    "start": "2026-10-30T18:30:00+01:00",
    "end": "2026-10-30T21:30:00+01:00",
    "location": "Deck & Dice Munich",
    "url": "https://www.dd-munich.de",
    "description": "",
    "all_day": false
  },
  {
    "title": "Deck & Dice \u2013 Friday Night Standard 18.30",
    "start": "2026-11-06T18:30:00+01:00",
    "end": "2026-11-06T21:30:00+01:00",
    "location": "Deck & Dice Munich",
    "url": "https://www.dd-munich.de",
    "description": "",
    "all_day": false
  },
  {
    "title": "Deck & Dice \u2013 Friday Night Standard 18.30",
    "start": "2026-11-13T18:30:00+01:00",
    "end": "2026-11-13T21:30:00+01:00",
    "location": "Deck & Dice Munich",
    "url": "https://www.dd-munich.de",
    "description": "",
    "all_day": false
  },
  {
    "title": "Deck & Dice \u2013 Friday Night Standard 18.30",
    "start": "2026-11-20T18:30:00+01:00",
    "end": "2026-11-20T21:30:00+01:00",
    "location": "Deck & Dice Munich",
    "url": "https://www.dd-munich.de",
    "description": "",
    "all_day": false
  },
  {
    "title": "Deck & Dice \u2013 Friday Night Standard 18.30",
    "start": "2026-11-27T18:30:00+01:00",
    "end": "2026-11-27T21:30:00+01:00",
    "location": "Deck & Dice Munich",
    "url": "https://www.dd-munich.de",
    "description": "",
    "all_day": false
  },
  {
    "title": "Deck & Dice \u2013 Friday Night Standard 18.30",
    "start": "2026-12-04T18:30:00+01:00",
    "end": "2026-12-04T21:30:00+01:00",
    "location": "Deck & Dice Munich",
    "url": "https://www.dd-munich.de",
    "description": "",
    "all_day": false
  },
  {
    "title": "Deck & Dice \u2013 Friday Night Standard 18.30",
    "start": "2026-12-11T18:30:00+01:00",
    "end": "2026-12-11T21:30:00+01:00",
    "location": "Deck & Dice Munich",
    "url": "https://www.dd-munich.de",
    "description": "",
    "all_day": false
  },
  {
    "title": "Deck & Dice \u2013 Friday Night Standard 18.30",
    "start": "2026-12-18T18:30:00+01:00",
    "end": "2026-12-18T21:30:00+01:00",
    "location": "Deck & Dice Munich",
    "url": "https://www.dd-munich.de",
    "description": "",
    "all_day": false
  },
  {
    "title": "Deck & Dice \u2013 Friday Night Modern 18.30",
    "start": "2026-04-10T18:30:00+02:00",
    "end": "2026-04-10T21:30:00+02:00",
    "location": "Deck & Dice Munich",
    "url": "https://www.dd-munich.de",
    "description": "",
    "all_day": false
  },
  {
    "title": "Deck & Dice \u2013 Friday Night Modern 18.30",
    "start": "2026-04-17T18:30:00+02:00",
    "end": "2026-04-17T21:30:00+02:00",
    "location": "Deck & Dice Munich",
    "url": "https://www.dd-munich.de",
    "description": "",
    "all_day": false
  },
  {
    "title": "Deck & Dice \u2013 Friday Night Modern 18.30",
    "start": "2026-04-24T18:30:00+02:00",
    "end": "2026-04-24T21:30:00+02:00",
    "location": "Deck & Dice Munich",
    "url": "https://www.dd-munich.de",
    "description": "",
    "all_day": false
  },
  {
    "title": "Deck & Dice \u2013 Friday Night Modern 18.30",
    "start": "2026-05-08T18:30:00+02:00",
    "end": "2026-05-08T21:30:00+02:00",
    "location": "Deck & Dice Munich",
    "url": "https://www.dd-munich.de",
    "description": "",
    "all_day": false
  },
  {
    "title": "Deck & Dice \u2013 Friday Night Modern 18.30",
    "start": "2026-05-15T18:30:00+02:00",
    "end": "2026-05-15T21:30:00+02:00",
    "location": "Deck & Dice Munich",
    "url": "https://www.dd-munich.de",
    "description": "",
    "all_day": false
  },
  {
    "title": "Deck & Dice \u2013 Friday Night Modern 18.30",
    "start": "2026-05-22T18:30:00+02:00",
    "end": "2026-05-22T21:30:00+02:00",
    "location": "Deck & Dice Munich",
    "url": "https://www.dd-munich.de",
    "description": "",
    "all_day": false
  },
  {
    "title": "Deck & Dice \u2013 Friday Night Modern 18.30",
    "start": "2026-05-29T18:30:00+02:00",
    "end": "2026-05-29T21:30:00+02:00",
    "location": "Deck & Dice Munich",
    "url": "https://www.dd-munich.de",
    "description": "",
    "all_day": false
  },
  {
    "title": "Deck & Dice \u2013 Friday Night Modern 18.30",
    "start": "2026-06-05T18:30:00+02:00",
    "end": "2026-06-05T21:30:00+02:00",
    "location": "Deck & Dice Munich",
    "url": "https://www.dd-munich.de",
    "description": "",
    "all_day": false
  },
  {
    "title": "Deck & Dice \u2013 Friday Night Modern 18.30",
    "start": "2026-06-12T18:30:00+02:00",
    "end": "2026-06-12T21:30:00+02:00",
    "location": "Deck & Dice Munich",
    "url": "https://www.dd-munich.de",
    "description": "",
    "all_day": false
  },
  {
    "title": "Deck & Dice \u2013 Friday Night Modern 18.30",
    "start": "2026-06-19T18:30:00+02:00",
    "end": "2026-06-19T21:30:00+02:00",
    "location": "Deck & Dice Munich",
    "url": "https://www.dd-munich.de",
    "description": "",
    "all_day": false
  },
  {
    "title": "Deck & Dice \u2013 Friday Night Modern 18.30",
    "start": "2026-06-26T18:30:00+02:00",
    "end": "2026-06-26T21:30:00+02:00",
    "location": "Deck & Dice Munich",
    "url": "https://www.dd-munich.de",
    "description": "",
    "all_day": false
  },
  {
    "title": "Deck & Dice \u2013 Friday Night Modern 18.30",
    "start": "2026-07-03T18:30:00+02:00",
    "end": "2026-07-03T21:30:00+02:00",
    "location": "Deck & Dice Munich",
    "url": "https://www.dd-munich.de",
    "description": "",
    "all_day": false
  },
  {
    "title": "Deck & Dice \u2013 Friday Night Modern 18.30",
    "start": "2026-07-10T18:30:00+02:00",
    "end": "2026-07-10T21:30:00+02:00",
    "location": "Deck & Dice Munich",
    "url": "https://www.dd-munich.de",
    "description": "",
    "all_day": false
  },
  {
    "title": "Deck & Dice \u2013 Friday Night Modern 18.30",
    "start": "2026-07-17T18:30:00+02:00",
    "end": "2026-07-17T21:30:00+02:00",
    "location": "Deck & Dice Munich",
    "url": "https://www.dd-munich.de",
    "description": "",
    "all_day": false
  },
  {
    "title": "Deck & Dice \u2013 Friday Night Modern 18.30",
    "start": "2026-07-24T18:30:00+02:00",
    "end": "2026-07-24T21:30:00+02:00",
    "location": "Deck & Dice Munich",
    "url": "https://www.dd-munich.de",
    "description": "",
    "all_day": false
  },
  {
    "title": "Deck & Dice \u2013 Friday Night Modern 18.30",
    "start": "2026-07-31T18:30:00+02:00",
    "end": "2026-07-31T21:30:00+02:00",
    "location": "Deck & Dice Munich",
    "url": "https://www.dd-munich.de",
    "description": "",
    "all_day": false
  },
  {
    "title": "Deck & Dice \u2013 Friday Night Modern 18.30",
    "start": "2026-08-07T18:30:00+02:00",
    "end": "2026-08-07T21:30:00+02:00",
    "location": "Deck & Dice Munich",
    "url": "https://www.dd-munich.de",
    "description": "",
    "all_day": false
  },
  {
    "title": "Deck & Dice \u2013 Friday Night Modern 18.30",
    "start": "2026-08-14T18:30:00+02:00",
    "end": "2026-08-14T21:30:00+02:00",
    "location": "Deck & Dice Munich",
    "url": "https://www.dd-munich.de",
    "description": "",
    "all_day": false
  },
  {
    "title": "Deck & Dice \u2013 Friday Night Modern 18.30",
    "start": "2026-08-21T18:30:00+02:00",
    "end": "2026-08-21T21:30:00+02:00",
    "location": "Deck & Dice Munich",
    "url": "https://www.dd-munich.de",
    "description": "",
    "all_day": false
  },
  {
    "title": "Deck & Dice \u2013 Friday Night Modern 18.30",
    "start": "2026-08-28T18:30:00+02:00",
    "end": "2026-08-28T21:30:00+02:00",
    "location": "Deck & Dice Munich",
    "url": "https://www.dd-munich.de",
    "description": "",
    "all_day": false
  },
  {
    "title": "Deck & Dice \u2013 Friday Night Modern 18.30",
    "start": "2026-09-04T18:30:00+02:00",
    "end": "2026-09-04T21:30:00+02:00",
    "location": "Deck & Dice Munich",
    "url": "https://www.dd-munich.de",
    "description": "",
    "all_day": false
  },
  {
    "title": "Deck & Dice \u2013 Friday Night Modern 18.30",
    "start": "2026-09-11T18:30:00+02:00",
    "end": "2026-09-11T21:30:00+02:00",
    "location": "Deck & Dice Munich",
    "url": "https://www.dd-munich.de",
    "description": "",
    "all_day": false
  },
  {
    "title": "Deck & Dice \u2013 Friday Night Modern 18.30",
    "start": "2026-09-18T18:30:00+02:00",
    "end": "2026-09-18T21:30:00+02:00",
    "location": "Deck & Dice Munich",
    "url": "https://www.dd-munich.de",
    "description": "",
    "all_day": false
  },
  {
    "title": "Deck & Dice \u2013 Friday Night Modern 18.30",
    "start": "2026-09-25T18:30:00+02:00",
    "end": "2026-09-25T21:30:00+02:00",
    "location": "Deck & Dice Munich",
    "url": "https://www.dd-munich.de",
    "description": "",
    "all_day": false
  },
  {
    "title": "Deck & Dice \u2013 Friday Night Modern 18.30",
    "start": "2026-10-02T18:30:00+02:00",
    "end": "2026-10-02T21:30:00+02:00",
    "location": "Deck & Dice Munich",
    "url": "https://www.dd-munich.de",
    "description": "",
    "all_day": false
  },
  {
    "title": "Deck & Dice \u2013 Friday Night Modern 18.30",
    "start": "2026-10-09T18:30:00+02:00",
    "end": "2026-10-09T21:30:00+02:00",
    "location": "Deck & Dice Munich",
    "url": "https://www.dd-munich.de",
    "description": "",
    "all_day": false
  },
  {
    "title": "Deck & Dice \u2013 Friday Night Modern 18.30",
    "start": "2026-10-16T18:30:00+02:00",
    "end": "2026-10-16T21:30:00+02:00",
    "location": "Deck & Dice Munich",
    "url": "https://www.dd-munich.de",
    "description": "",
    "all_day": false
  },
  {
    "title": "Deck & Dice \u2013 Friday Night Modern 18.30",
    "start": "2026-10-23T18:30:00+02:00",
    "end": "2026-10-23T21:30:00+02:00",
    "location": "Deck & Dice Munich",
    "url": "https://www.dd-munich.de",
    "description": "",
    "all_day": false
  },
  {
    "title": "Deck & Dice \u2013 Friday Night Modern 18.30",
    "start": "2026-10-30T18:30:00+01:00",
    "end": "2026-10-30T21:30:00+01:00",
    "location": "Deck & Dice Munich",
    "url": "https://www.dd-munich.de",
    "description": "",
    "all_day": false
  },
  {
    "title": "Deck & Dice \u2013 Friday Night Modern 18.30",
    "start": "2026-11-06T18:30:00+01:00",
    "end": "2026-11-06T21:30:00+01:00",
    "location": "Deck & Dice Munich",
    "url": "https://www.dd-munich.de",
    "description": "",
    "all_day": false
  },
  {
    "title": "Deck & Dice \u2013 Friday Night Modern 18.30",
    "start": "2026-11-13T18:30:00+01:00",
    "end": "2026-11-13T21:30:00+01:00",
    "location": "Deck & Dice Munich",
    "url": "https://www.dd-munich.de",
    "description": "",
    "all_day": false
  },
  {
    "title": "Deck & Dice \u2013 Friday Night Modern 18.30",
    "start": "2026-11-20T18:30:00+01:00",
    "end": "2026-11-20T21:30:00+01:00",
    "location": "Deck & Dice Munich",
    "url": "https://www.dd-munich.de",
    "description": "",
    "all_day": false
  },
  {
    "title": "Deck & Dice \u2013 Friday Night Modern 18.30",
    "start": "2026-11-27T18:30:00+01:00",
    "end": "2026-11-27T21:30:00+01:00",
    "location": "Deck & Dice Munich",
    "url": "https://www.dd-munich.de",
    "description": "",
    "all_day": false
  },
  {
    "title": "Deck & Dice \u2013 Friday Night Modern 18.30",
    "start": "2026-12-04T18:30:00+01:00",
    "end": "2026-12-04T21:30:00+01:00",
    "location": "Deck & Dice Munich",
    "url": "https://www.dd-munich.de",
    "description": "",
    "all_day": false
  },
  {
    "title": "Deck & Dice \u2013 Friday Night Modern 18.30",
    "start": "2026-12-11T18:30:00+01:00",
    "end": "2026-12-11T21:30:00+01:00",
    "location": "Deck & Dice Munich",
    "url": "https://www.dd-munich.de",
    "description": "",
    "all_day": false
  },
  {
    "title": "Deck & Dice \u2013 Friday Night Modern 18.30",
    "start": "2026-12-18T18:30:00+01:00",
    "end": "2026-12-18T21:30:00+01:00",
    "location": "Deck & Dice Munich",
    "url": "https://www.dd-munich.de",
    "description": "",
    "all_day": false
  },
  {
    "title": "Countdown \u2013 Monatliches Magic Legacy Turnier",
    "start": "2026-03-29T11:00:00+02:00",
    "end": "2026-03-29T14:00:00+02:00",
    "location": "Countdown Spielewelt Landsberg",
    "url": "https://countdown-spielewelt.de/event/monatliches-magic-legacy-turnier-yej6rvv/",
    "description": "Companion Code: YEJ6RVV\nCompanion Link: https://magic.wizards.com/en/products/companion-app/tournament/YEJ6RVV",
    "all_day": false
  },
  {
    "title": "Countdown \u2013 Monatliches Magic Legacy Turnier",
    "start": "2026-04-26T11:00:00+02:00",
    "end": "2026-04-26T14:00:00+02:00",
    "location": "Countdown Spielewelt Landsberg",
    "url": "https://countdown-spielewelt.de/event/monatliches-magic-legacy-turnier-ez6ex5r/",
    "description": "Casual Schweizer System Proxys erlaubt Max. Teilnehmer 64 , es werden bis 16 Teilnehmer 4 Runden, 17-32 5 Runden und 33-64 6 Runden gespielt. Nach der H\u00e4lfte der gespielten Runden [\u2026]\nCompanion Code: EZ6EX5R\nCompanion Link: https://magic.wizards.com/en/products/companion-app/tournament/EZ6EX5R",
    "all_day": false
  },
  {
    "title": "Countdown \u2013 Monatliches Magic Legacy Turnier",
    "start": "2026-05-31T11:00:00+02:00",
    "end": "2026-05-31T14:00:00+02:00",
    "location": "Countdown Spielewelt Landsberg",
    "url": "https://countdown-spielewelt.de/event/monatliches-magic-legacy-turnier-v2wegzd/2026-05-31/",
    "description": "Casual Schweizer System Proxys erlaubt Max. Teilnehmer 64 , es werden bis 16 Teilnehmer 4 Runden, 17-32 5 Runden und 33-64 6 Runden gespielt. Nach der H\u00e4lfte der gespielten Runden [\u2026]",
    "all_day": false
  },
  {
    "title": "Countdown \u2013 Monatliches Magic Legacy Turnier",
    "start": "2026-06-28T11:00:00+02:00",
    "end": "2026-06-28T14:00:00+02:00",
    "location": "Countdown Spielewelt Landsberg",
    "url": "https://countdown-spielewelt.de/event/monatliches-magic-legacy-turnier-v2wegzd/2026-06-28/",
    "description": "Casual Schweizer System Proxys erlaubt Max. Teilnehmer 64 , es werden bis 16 Teilnehmer 4 Runden, 17-32 5 Runden und 33-64 6 Runden gespielt. Nach der H\u00e4lfte der gespielten Runden [\u2026]",
    "all_day": false
  },
  {
    "title": "Countdown \u2013 Monatliches Magic Legacy Turnier",
    "start": "2026-07-26T11:00:00+02:00",
    "end": "2026-07-26T14:00:00+02:00",
    "location": "Countdown Spielewelt Landsberg",
    "url": "https://countdown-spielewelt.de/event/monatliches-magic-legacy-turnier-v2wegzd/2026-07-26/",
    "description": "Casual Schweizer System Proxys erlaubt Max. Teilnehmer 64 , es werden bis 16 Teilnehmer 4 Runden, 17-32 5 Runden und 33-64 6 Runden gespielt. Nach der H\u00e4lfte der gespielten Runden [\u2026]",
    "all_day": false
  },
  {
    "title": "Countdown \u2013 Monatliches Magic Legacy Turnier",
    "start": "2026-08-23T11:00:00+02:00",
    "end": "2026-08-23T14:00:00+02:00",
    "location": "Countdown Spielewelt Landsberg",
    "url": "https://countdown-spielewelt.de/event/monatliches-magic-legacy-turnier-v2wegzd/2026-08-23/",
    "description": "Casual Schweizer System Proxys erlaubt Max. Teilnehmer 64 , es werden bis 16 Teilnehmer 4 Runden, 17-32 5 Runden und 33-64 6 Runden gespielt. Nach der H\u00e4lfte der gespielten Runden [\u2026]",
    "all_day": false
  },
  {
    "title": "Countdown \u2013 Monatliches Magic Legacy Turnier",
    "start": "2026-09-27T11:00:00+02:00",
    "end": "2026-09-27T14:00:00+02:00",
    "location": "Countdown Spielewelt Landsberg",
    "url": "https://countdown-spielewelt.de/event/monatliches-magic-legacy-turnier-v2wegzd/2026-09-27/",
    "description": "Casual Schweizer System Proxys erlaubt Max. Teilnehmer 64 , es werden bis 16 Teilnehmer 4 Runden, 17-32 5 Runden und 33-64 6 Runden gespielt. Nach der H\u00e4lfte der gespielten Runden [\u2026]",
    "all_day": false
  },
  {
    "title": "Countdown \u2013 Monatliches Magic Legacy Turnier",
    "start": "2026-10-25T11:00:00+01:00",
    "end": "2026-10-25T14:00:00+01:00",
    "location": "Countdown Spielewelt Landsberg",
    "url": "https://countdown-spielewelt.de/event/monatliches-magic-legacy-turnier-v2wegzd/2026-10-25/",
    "description": "Casual Schweizer System Proxys erlaubt Max. Teilnehmer 64 , es werden bis 16 Teilnehmer 4 Runden, 17-32 5 Runden und 33-64 6 Runden gespielt. Nach der H\u00e4lfte der gespielten Runden [\u2026]",
    "all_day": false
  },
  {
    "title": "Countdown \u2013 Monatliches Magic Legacy Turnier",
    "start": "2026-11-22T11:00:00+01:00",
    "end": "2026-11-22T14:00:00+01:00",
    "location": "Countdown Spielewelt Landsberg",
    "url": "https://countdown-spielewelt.de/event/monatliches-magic-legacy-turnier-v2wegzd/2026-11-22/",
    "description": "Casual Schweizer System Proxys erlaubt Max. Teilnehmer 64 , es werden bis 16 Teilnehmer 4 Runden, 17-32 5 Runden und 33-64 6 Runden gespielt. Nach der H\u00e4lfte der gespielten Runden [\u2026]",
    "all_day": false
  },
  {
    "title": "Countdown \u2013 Monatliches Magic Legacy Turnier",
    "start": "2026-12-27T11:00:00+01:00",
    "end": "2026-12-27T14:00:00+01:00",
    "location": "Countdown Spielewelt Landsberg",
    "url": "https://countdown-spielewelt.de/event/monatliches-magic-legacy-turnier-v2wegzd/2026-12-27/",
    "description": "Casual Schweizer System Proxys erlaubt Max. Teilnehmer 64 , es werden bis 16 Teilnehmer 4 Runden, 17-32 5 Runden und 33-64 6 Runden gespielt. Nach der H\u00e4lfte der gespielten Runden [\u2026]",
    "all_day": false
  },
  {
    "title": "Countdown \u2013 Monatliches Magic Legacy Turnier",
    "start": "2027-01-24T11:00:00+01:00",
    "end": "2027-01-24T14:00:00+01:00",
    "location": "Countdown Spielewelt Landsberg",
    "url": "https://countdown-spielewelt.de/event/monatliches-magic-legacy-turnier-v2wegzd/2027-01-24/",
    "description": "Casual Schweizer System Proxys erlaubt Max. Teilnehmer 64 , es werden bis 16 Teilnehmer 4 Runden, 17-32 5 Runden und 33-64 6 Runden gespielt. Nach der H\u00e4lfte der gespielten Runden [\u2026]",
    "all_day": false
  },
  {
    "title": "Countdown \u2013 Monatliches Magic Legacy Turnier",
    "start": "2027-02-28T11:00:00+01:00",
    "end": "2027-02-28T14:00:00+01:00",
    "location": "Countdown Spielewelt Landsberg",
    "url": "https://countdown-spielewelt.de/event/monatliches-magic-legacy-turnier-v2wegzd/2027-02-28/",
    "description": "Casual Schweizer System Proxys erlaubt Max. Teilnehmer 64 , es werden bis 16 Teilnehmer 4 Runden, 17-32 5 Runden und 33-64 6 Runden gespielt. Nach der H\u00e4lfte der gespielten Runden [\u2026]",
    "all_day": false
  },
  {
    "title": "Countdown \u2013 Monatliches Magic Legacy Turnier",
    "start": "2027-03-28T11:00:00+02:00",
    "end": "2027-03-28T14:00:00+02:00",
    "location": "Countdown Spielewelt Landsberg",
    "url": "https://countdown-spielewelt.de/event/monatliches-magic-legacy-turnier-v2wegzd/2027-03-28/",
    "description": "Casual Schweizer System Proxys erlaubt Max. Teilnehmer 64 , es werden bis 16 Teilnehmer 4 Runden, 17-32 5 Runden und 33-64 6 Runden gespielt. Nach der H\u00e4lfte der gespielten Runden [\u2026]",
    "all_day": false
  },
  {
    "title": "Countdown \u2013 Monatliches Magic Legacy Turnier",
    "start": "2027-04-25T11:00:00+02:00",
    "end": "2027-04-25T14:00:00+02:00",
    "location": "Countdown Spielewelt Landsberg",
    "url": "https://countdown-spielewelt.de/event/monatliches-magic-legacy-turnier-v2wegzd/2027-04-25/",
    "description": "Casual Schweizer System Proxys erlaubt Max. Teilnehmer 64 , es werden bis 16 Teilnehmer 4 Runden, 17-32 5 Runden und 33-64 6 Runden gespielt. Nach der H\u00e4lfte der gespielten Runden [\u2026]",
    "all_day": false
  },
  {
    "title": "Countdown \u2013 Monatliches Magic Legacy Turnier",
    "start": "2027-05-23T11:00:00+02:00",
    "end": "2027-05-23T14:00:00+02:00",
    "location": "Countdown Spielewelt Landsberg",
    "url": "https://countdown-spielewelt.de/event/monatliches-magic-legacy-turnier-v2wegzd/2027-05-23/",
    "description": "Casual Schweizer System Proxys erlaubt Max. Teilnehmer 64 , es werden bis 16 Teilnehmer 4 Runden, 17-32 5 Runden und 33-64 6 Runden gespielt. Nach der H\u00e4lfte der gespielten Runden [\u2026]",
    "all_day": false
  },
  {
    "title": "Countdown \u2013 Monatliches Magic Legacy Turnier",
    "start": "2027-06-27T11:00:00+02:00",
    "end": "2027-06-27T14:00:00+02:00",
    "location": "Countdown Spielewelt Landsberg",
    "url": "https://countdown-spielewelt.de/event/monatliches-magic-legacy-turnier-v2wegzd/2027-06-27/",
    "description": "Casual Schweizer System Proxys erlaubt Max. Teilnehmer 64 , es werden bis 16 Teilnehmer 4 Runden, 17-32 5 Runden und 33-64 6 Runden gespielt. Nach der H\u00e4lfte der gespielten Runden [\u2026]",
    "all_day": false
  },
  {
    "title": "Countdown \u2013 Monatliches Magic Legacy Turnier",
    "start": "2027-07-25T11:00:00+02:00",
    "end": "2027-07-25T14:00:00+02:00",
    "location": "Countdown Spielewelt Landsberg",
    "url": "https://countdown-spielewelt.de/event/monatliches-magic-legacy-turnier-v2wegzd/2027-07-25/",
    "description": "Casual Schweizer System Proxys erlaubt Max. Teilnehmer 64 , es werden bis 16 Teilnehmer 4 Runden, 17-32 5 Runden und 33-64 6 Runden gespielt. Nach der H\u00e4lfte der gespielten Runden [\u2026]",
    "all_day": false
  },
  {
    "title": "Countdown \u2013 Monatliches Magic Legacy Turnier",
    "start": "2027-08-22T11:00:00+02:00",
    "end": "2027-08-22T14:00:00+02:00",
    "location": "Countdown Spielewelt Landsberg",
    "url": "https://countdown-spielewelt.de/event/monatliches-magic-legacy-turnier-v2wegzd/2027-08-22/",
    "description": "Casual Schweizer System Proxys erlaubt Max. Teilnehmer 64 , es werden bis 16 Teilnehmer 4 Runden, 17-32 5 Runden und 33-64 6 Runden gespielt. Nach der H\u00e4lfte der gespielten Runden [\u2026]",
    "all_day": false
  },
  {
    "title": "Countdown \u2013 Monatliches Magic Legacy Turnier",
    "start": "2027-09-26T11:00:00+02:00",
    "end": "2027-09-26T14:00:00+02:00",
    "location": "Countdown Spielewelt Landsberg",
    "url": "https://countdown-spielewelt.de/event/monatliches-magic-legacy-turnier-v2wegzd/2027-09-26/",
    "description": "Casual Schweizer System Proxys erlaubt Max. Teilnehmer 64 , es werden bis 16 Teilnehmer 4 Runden, 17-32 5 Runden und 33-64 6 Runden gespielt. Nach der H\u00e4lfte der gespielten Runden [\u2026]",
    "all_day": false
  },
  {
    "title": "Countdown \u2013 Monatliches Magic Legacy Turnier",
    "start": "2027-10-24T11:00:00+02:00",
    "end": "2027-10-24T14:00:00+02:00",
    "location": "Countdown Spielewelt Landsberg",
    "url": "https://countdown-spielewelt.de/event/monatliches-magic-legacy-turnier-v2wegzd/2027-10-24/",
    "description": "Casual Schweizer System Proxys erlaubt Max. Teilnehmer 64 , es werden bis 16 Teilnehmer 4 Runden, 17-32 5 Runden und 33-64 6 Runden gespielt. Nach der H\u00e4lfte der gespielten Runden [\u2026]",
    "all_day": false
  },
  {
    "title": "Countdown \u2013 Monatliches Magic Legacy Turnier",
    "start": "2027-11-28T11:00:00+01:00",
    "end": "2027-11-28T14:00:00+01:00",
    "location": "Countdown Spielewelt Landsberg",
    "url": "https://countdown-spielewelt.de/event/monatliches-magic-legacy-turnier-v2wegzd/2027-11-28/",
    "description": "Casual Schweizer System Proxys erlaubt Max. Teilnehmer 64 , es werden bis 16 Teilnehmer 4 Runden, 17-32 5 Runden und 33-64 6 Runden gespielt. Nach der H\u00e4lfte der gespielten Runden [\u2026]",
    "all_day": false
  },
  {
    "title": "Countdown \u2013 Monatliches Magic Legacy Turnier",
    "start": "2028-01-23T11:00:00+01:00",
    "end": "2028-01-23T14:00:00+01:00",
    "location": "Countdown Spielewelt Landsberg",
    "url": "https://countdown-spielewelt.de/event/monatliches-magic-legacy-turnier-v2wegzd/2028-01-23/",
    "description": "Casual Schweizer System Proxys erlaubt Max. Teilnehmer 64 , es werden bis 16 Teilnehmer 4 Runden, 17-32 5 Runden und 33-64 6 Runden gespielt. Nach der H\u00e4lfte der gespielten Runden [\u2026]",
    "all_day": false
  },
  {
    "title": "Countdown \u2013 Monatliches Magic Legacy Turnier",
    "start": "2028-02-27T11:00:00+01:00",
    "end": "2028-02-27T14:00:00+01:00",
    "location": "Countdown Spielewelt Landsberg",
    "url": "https://countdown-spielewelt.de/event/monatliches-magic-legacy-turnier-v2wegzd/2028-02-27/",
    "description": "Casual Schweizer System Proxys erlaubt Max. Teilnehmer 64 , es werden bis 16 Teilnehmer 4 Runden, 17-32 5 Runden und 33-64 6 Runden gespielt. Nach der H\u00e4lfte der gespielten Runden [\u2026]",
    "all_day": false
  },
  {
    "title": "Racoon Rises \u2013 MtG | Monthly Legacy ",
    "start": "2026-04-12T11:00:00+02:00",
    "end": "2026-04-12T18:00:00+02:00",
    "location": "Racoon Rises, Ulm",
    "url": "https://www.google.com/calendar/event?eid=N3U1YjNvcTZwaG4ybDcyZXNna2Z1anZoZmYgY183ZjA5MGYxMGRiYjg0M2MwYmFjOTFlZDU4NTk0Yzg1YjdhYzU5YzEyZDE3NjRiMzRhNTg2ZGQwMWNhN2E4NTAyQGc",
    "description": "Teilnahmegeb\u00fchr: 25.00\u20ac",
    "all_day": false
  },
  {
    "title": "Racoon Rises \u2013 MtG | Monthly Legacy ",
    "start": "2026-05-03T11:00:00+02:00",
    "end": "2026-05-03T18:00:00+02:00",
    "location": "Racoon Rises, Ulm",
    "url": "https://www.google.com/calendar/event?eid=NDE3dWswZWI5MmFqbzUxcTBrYTZlYWt0MnEgY183ZjA5MGYxMGRiYjg0M2MwYmFjOTFlZDU4NTk0Yzg1YjdhYzU5YzEyZDE3NjRiMzRhNTg2ZGQwMWNhN2E4NTAyQGc",
    "description": "Teilnahmegeb\u00fchr: 25.00\u20ac",
    "all_day": false
  },
  {
    "title": "MTGO \u2013 Modern Last Chance",
    "start": "2026-03-23T23:00:00+01:00",
    "end": "2026-03-24T01:00:00+01:00",
    "location": "MTGO",
    "url": "",
    "description": "",
    "all_day": false
  },
  {
    "title": "MTGO \u2013 Modern Last Chance",
    "start": "2026-03-24T15:00:00+01:00",
    "end": "2026-03-24T17:00:00+01:00",
    "location": "MTGO",
    "url": "",
    "description": "",
    "all_day": false
  },
  {
    "title": "MTGO \u2013 Premodern Challenge 32",
    "start": "2026-03-24T16:00:00+01:00",
    "end": "2026-03-24T18:00:00+01:00",
    "location": "MTGO",
    "url": "",
    "description": "",
    "all_day": false
  },
  {
    "title": "MTGO \u2013 Modern Challenge 64",
    "start": "2026-03-24T20:00:00+01:00",
    "end": "2026-03-24T22:00:00+01:00",
    "location": "MTGO",
    "url": "",
    "description": "",
    "all_day": false
  },
  {
    "title": "MTGO \u2013 Modern Showcase Qualifier",
    "start": "2026-03-28T15:00:00+01:00",
    "end": "2026-03-28T19:00:00+01:00",
    "location": "MTGO",
    "url": "",
    "description": "",
    "all_day": false
  },
  {
    "title": "MTGO \u2013 Modern Preliminary",
    "start": "2026-03-26T07:00:00+01:00",
    "end": "2026-03-26T09:00:00+01:00",
    "location": "MTGO",
    "url": "",
    "description": "",
    "all_day": false
  },
  {
    "title": "MTGO \u2013 Modern Challenge 64",
    "start": "2026-03-26T13:00:00+01:00",
    "end": "2026-03-26T15:00:00+01:00",
    "location": "MTGO",
    "url": "",
    "description": "",
    "all_day": false
  },
  {
    "title": "MTGO \u2013 Premodern Challenge 32",
    "start": "2026-03-26T17:00:00+01:00",
    "end": "2026-03-26T19:00:00+01:00",
    "location": "MTGO",
    "url": "",
    "description": "",
    "all_day": false
  },
  {
    "title": "MTGO \u2013 Modern Preliminary",
    "start": "2026-03-26T20:00:00+01:00",
    "end": "2026-03-26T22:00:00+01:00",
    "location": "MTGO",
    "url": "",
    "description": "",
    "all_day": false
  },
  {
    "title": "MTGO \u2013 Modern Preliminary",
    "start": "2026-03-27T02:00:00+01:00",
    "end": "2026-03-27T04:00:00+01:00",
    "location": "MTGO",
    "url": "",
    "description": "",
    "all_day": false
  },
  {
    "title": "MTGO \u2013 Modern Preliminary",
    "start": "2026-03-27T11:00:00+01:00",
    "end": "2026-03-27T13:00:00+01:00",
    "location": "MTGO",
    "url": "",
    "description": "",
    "all_day": false
  },
  {
    "title": "MTGO \u2013 Premodern Challenge 32",
    "start": "2026-03-27T20:00:00+01:00",
    "end": "2026-03-27T22:00:00+01:00",
    "location": "MTGO",
    "url": "",
    "description": "",
    "all_day": false
  },
  {
    "title": "MTGO \u2013 Modern Challenge 32",
    "start": "2026-03-28T01:00:00+01:00",
    "end": "2026-03-28T03:00:00+01:00",
    "location": "MTGO",
    "url": "",
    "description": "",
    "all_day": false
  },
  {
    "title": "MTGO \u2013 Modern Challenge 32",
    "start": "2026-03-28T06:00:00+01:00",
    "end": "2026-03-28T08:00:00+01:00",
    "location": "MTGO",
    "url": "",
    "description": "",
    "all_day": false
  },
  {
    "title": "MTGO \u2013 Modern Challenge 64",
    "start": "2026-03-28T15:30:00+01:00",
    "end": "2026-03-28T17:30:00+01:00",
    "location": "MTGO",
    "url": "",
    "description": "",
    "all_day": false
  },
  {
    "title": "MTGO \u2013 Premodern Challenge 32",
    "start": "2026-03-28T22:30:00+01:00",
    "end": "2026-03-29T00:30:00+01:00",
    "location": "MTGO",
    "url": "",
    "description": "",
    "all_day": false
  },
  {
    "title": "MTGO \u2013 Modern Challenge 32",
    "start": "2026-03-29T01:00:00+01:00",
    "end": "2026-03-29T03:00:00+02:00",
    "location": "MTGO",
    "url": "",
    "description": "",
    "all_day": false
  },
  {
    "title": "MTGO \u2013 Modern Challenge 32",
    "start": "2026-03-29T11:00:00+02:00",
    "end": "2026-03-29T13:00:00+02:00",
    "location": "MTGO",
    "url": "",
    "description": "",
    "all_day": false
  },
  {
    "title": "MTGO \u2013 Modern Preliminary",
    "start": "2026-03-29T16:00:00+02:00",
    "end": "2026-03-29T18:00:00+02:00",
    "location": "MTGO",
    "url": "",
    "description": "",
    "all_day": false
  },
  {
    "title": "MTGO \u2013 Modern Challenge 32",
    "start": "2026-03-30T01:00:00+02:00",
    "end": "2026-03-30T03:00:00+02:00",
    "location": "MTGO",
    "url": "",
    "description": "",
    "all_day": false
  },
  {
    "title": "MTGO \u2013 Modern Challenge 32",
    "start": "2026-03-30T14:00:00+02:00",
    "end": "2026-03-30T16:00:00+02:00",
    "location": "MTGO",
    "url": "",
    "description": "",
    "all_day": false
  },
  {
    "title": "MTGO \u2013 Modern Preliminary",
    "start": "2026-03-30T22:00:00+02:00",
    "end": "2026-03-31T00:00:00+02:00",
    "location": "MTGO",
    "url": "",
    "description": "",
    "all_day": false
  },
  {
    "title": "MTGO \u2013 Modern Preliminary",
    "start": "2026-03-31T04:00:00+02:00",
    "end": "2026-03-31T06:00:00+02:00",
    "location": "MTGO",
    "url": "",
    "description": "",
    "all_day": false
  },
  {
    "title": "MTGO \u2013 Modern Preliminary",
    "start": "2026-03-31T10:00:00+02:00",
    "end": "2026-03-31T12:00:00+02:00",
    "location": "MTGO",
    "url": "",
    "description": "",
    "all_day": false
  },
  {
    "title": "MTGO \u2013 Premodern Challenge 32",
    "start": "2026-03-31T16:00:00+02:00",
    "end": "2026-03-31T18:00:00+02:00",
    "location": "MTGO",
    "url": "",
    "description": "",
    "all_day": false
  },
  {
    "title": "MTGO \u2013 Modern Challenge 64",
    "start": "2026-03-31T20:00:00+02:00",
    "end": "2026-03-31T22:00:00+02:00",
    "location": "MTGO",
    "url": "",
    "description": "",
    "all_day": false
  },
  {
    "title": "MTGO \u2013 Modern Preliminary",
    "start": "2026-04-01T00:00:00+02:00",
    "end": "2026-04-01T02:00:00+02:00",
    "location": "MTGO",
    "url": "",
    "description": "",
    "all_day": false
  },
  {
    "title": "MTGO \u2013 Modern Preliminary",
    "start": "2026-04-01T09:00:00+02:00",
    "end": "2026-04-01T11:00:00+02:00",
    "location": "MTGO",
    "url": "",
    "description": "",
    "all_day": false
  },
  {
    "title": "MTGO \u2013 Modern Challenge 32",
    "start": "2026-04-01T16:00:00+02:00",
    "end": "2026-04-01T18:00:00+02:00",
    "location": "MTGO",
    "url": "",
    "description": "",
    "all_day": false
  },
  {
    "title": "MTGO \u2013 Modern Challenge 64",
    "start": "2026-03-25T16:00:00+01:00",
    "end": "2026-03-25T18:00:00+01:00",
    "location": "MTGO",
    "url": "",
    "description": "",
    "all_day": false
  },
  {
    "title": "MTGO \u2013 Modern Challenge 64",
    "start": "2026-03-27T15:00:00+01:00",
    "end": "2026-03-27T17:00:00+01:00",
    "location": "MTGO",
    "url": "",
    "description": "",
    "all_day": false
  },
  {
    "title": "Racoon Rises \u2013 Legacy Qualifier",
    "start": "2026-05-31T11:00:00+02:00",
    "end": "2026-05-31T17:00:00+02:00",
    "location": "Racoon Rises, Ulm",
    "url": "https://www.google.com/calendar/event?eid=MGVjZGNpYTJiOWQ2NDI4bDFxNm9laDhuY2wgY183ZjA5MGYxMGRiYjg0M2MwYmFjOTFlZDU4NTk0Yzg1YjdhYzU5YzEyZDE3NjRiMzRhNTg2ZGQwMWNhN2E4NTAyQGc",
    "description": "",
    "all_day": false
  },
  {
    "title": "Fanfinity \u2013 Magic Spotlight Series London 2026",
    "start": "2026-03-06T00:00:00",
    "end": "2026-03-09T00:00:00",
    "location": "Online",
    "url": "https://www.fanfinity.gg/event/magic-spotlight-series-london-2026/",
    "description": "Event von Fanfinity: Magic Spotlight Series London 2026\nhttps://www.fanfinity.gg/event/magic-spotlight-series-london-2026/",
    "all_day": true
  },
  {
    "title": "Racoon Rises \u2013 Legacy ELM Qualifier",
    "start": "2026-05-31T11:00:00+02:00",
    "end": "2026-05-31T17:00:00+02:00",
    "location": "Racoon Rises, Ulm",
    "url": "https://www.google.com/calendar/event?eid=MGVjZGNpYTJiOWQ2NDI4bDFxNm9laDhuY2wgY183ZjA5MGYxMGRiYjg0M2MwYmFjOTFlZDU4NTk0Yzg1YjdhYzU5YzEyZDE3NjRiMzRhNTg2ZGQwMWNhN2E4NTAyQGc",
    "description": "",
    "all_day": false
  }
]